Workbook

Sheet Start_Here
A1: Project | B1: Marketing Campaign ROI Analysis
A2: Purpose | B2: Analyze multi-channel marketing performance and recommend budget improvements.
A3: Company type | B3: Digital solutions / IT services company
A4: Important honesty note | B4: This project uses realistic synthetic data created for portfolio demonstration. It is not confidential company data.
A5: Time period | B5: December 2023 to December 2024
A6: Main question | B6: Which channels and campaigns produce quality leads, revenue, and ROI, and where is ad spend wasted?
A7: How to read workbook | B7: Start with Dashboard, then Channel_KPIs, Campaign_KPIs, Lead_Quality, Recommendations, and Cleaned_Daily.
A8: Skills shown | B8: Data cleaning, campaign KPI calculation, lead quality analysis, ROI/ROAS analysis, reporting, business recommendations.

Sheet Data_Dictionary
A1: Field | B1: Meaning | C1: Why it matters
A2: Spend USD | B2: Money spent on paid campaigns or email tools/design. | C2: Helps measure efficiency and ROI.
A3: Impressions | B3: How many times ads/emails/organic results were seen. | C3: Shows awareness volume.
A4: Clicks | B4: How many people clicked. | C4: Shows interest and traffic intent.
A5: Sessions | B5: Website visits attributed to the source. | C5: Connects campaign traffic to website behavior.
A6: Leads | B6: People who submitted a form or became a campaign conversion. | C6: Measures lead generation.
A7: Qualified Leads | B7: Leads that sales considered useful or relevant. | C7: Prevents judging marketing only by lead volume.
A8: Customers | B8: Leads that became paying customers. | C8: Shows business outcome.
A9: Revenue USD | B9: Closed revenue linked back to the source/campaign. | C9: Used for ROI and ROAS.
A10: CTR | B10: Clicks divided by impressions. | C10: Shows if message/creative attracts attention.
A11: CPC | B11: Spend divided by clicks. | C11: Shows traffic cost.
A12: Conversion Rate | B12: Leads divided by clicks. | C12: Shows landing page and offer performance.
... A16: ROI | B16: (Revenue - Spend) divided by spend. | C16: Shows profit-like return after cost.

Sheet Raw_Meta
A1: Reporting starts | B1: Reporting ends | C1: Campaign name | D1: Campaign ID | E1: Ad set name | F1: Ad set ID | G1: Ad name | H1: Ad ID | I1: Platform | J1: Delivery status | K1: Attribution setting | L1: Objective | M1: Result type | N1: Results | O1: Amount spent (USD) | P1: Impressions | Q1: Reach | R1: Frequency | S1: Link clicks | T1: Landing page views | U1: CTR (link click-through rate) | V1: CPC (cost per link click) | W1: CPM (cost per 1,000 impressions) | X1: Leads | Y1: Cost per lead | Z1: Service promoted | AA1: Landing page
A2: 2023-12-01 | B2: 2023-12-01 | C2: DA_Dec23_Website_Lead_Generation | D2: META-001 | E2: Small Business Owners - Facebook | F2: AS-001-1 | G2: Service Carousel | H2: AD-001-1-FA | I2: Facebook | J2: active | K2: 7-day click or 1-day view | L2: Lead generation | M2: Leads | N2: 4 | O2: 25.01 | P2: 6100 | Q2: 5174 | R2: 1.18 | S2: 100 | T2: 77 | U2: 1.64 | V2: 0.25 | W2: 4.1 | X2: 4 | Y2: 6.25 | Z2: Website Development | AA2: /services/website-development
A3: 2023-12-01 | B3: 2023-12-01 | C3: DA_Dec23_Website_Lead_Generation | D3: META-001 | E3: Startup Founders - Facebook | F3: AS-001-2 | G3: Service Carousel | H3: AD-001-2-FA | I3: Facebook | J3: active | K3: 7-day click or 1-day view | L3: Lead generation | M3: Leads | N3: 1 | O3: 16.69 | P3: 3214 | Q3: 2628 | R3: 1.22 | S3: 50 | T3: 41 | U3: 1.56 | V3: 0.33 | W3: 5.19 | X3: 1 | Y3: 16.69 | Z3: Website Development | AA3: /services/website-development
A4: 2023-12-01 | B4: 2023-12-01 | C4: DA_Dec23_Website_Lead_Generation | D4: META-001 | E4: Small Business Owners - Instagram | F4: AS-001-1 | G4: Lead Form Static | H4: AD-001-1-IN | I4: Instagram | J4: active | K4: 7-day click or 1-day view | L4: Lead generation | M4: Leads | N4: 2 | O4: 27.69 | P4: 4657 | Q4: 4113 | R4: 1.13 | S4: 61 | T4: 45 | U4: 1.31 | V4: 0.45 | W4: 5.94 | X4: 2 | Y4: 13.85 | Z4: Website Development | AA4: /services/website-development
A5: 2023-12-01 | B5: 2023-12-01 | C5: DA_Dec23_Website_Lead_Generation | D5: META-001 | E5: Startup Founders - Instagram | F5: AS-001-2 | G5: Service Carousel | H5: AD-001-2-IN | I5: Instagram | J5: active | K5: 7-day click or 1-day view | L5: Lead generation | M5: Leads | N5: 0 | O5: 20.09 | P5: 2890 | Q5: 2627 | R5: 1.1 | S5: 35 | T5: 28 | U5: 1.21 | V5: 0.57 | W5: 6.95 | X5: 0 | Y5: 0 | Z5: Website Development | AA5: /services/website-development
A6: 2023-12-02 | B6: 2023-12-02 | C6: DA_Dec23_Website_Lead_Generation | D6: META-001 | E6: Small Business Owners - Facebook | F6: AS-001-1 | G6: Service Carousel | H6: AD-001-1-FA | I6: Facebook | J6: active | K6: 7-day click or 1-day view | L6: Lead generation | M6: Leads | N6: 0 | O6: 19.7 | P6: 3181 | Q6: 2544 | R6: 1.25 | S6: 30 | T6: 25 | U6: 0.94 | V6: 0.66 | W6: 6.19 | X6: 0 | Y6: 0 | Z6: Website Development | AA6: /services/website-development
A7: 2023-12-02 | B7: 2023-12-02 | C7: DA_Dec23_Website_Lead_Generation | D7: META-001 | E7: Startup Founders - Facebook | F7: AS-001-2 | G7: Lead Form Static | H7: AD-001-2-FA | I7: Facebook | J7: active | K7: 7-day click or 1-day view | L7: Lead generation | M7: Leads | N7: 2 | O7: 18.21 | P7: 2516 | Q7: 2284 | R7: 1.1 | S7: 28 | T7: 21 | U7: 1.11 | V7: 0.65 | W7: 7.24 | X7: 2 | Y7: 9.11 | Z7: Website Development | AA7: /services/website-development
A8: 2023-12-02 | B8: 2023-12-02 | C8: DA_Dec23_Website_Lead_Generation | D8: META-001 | E8: Small Business Owners - Instagram | F8: AS-001-1 | G8: Lead Form Static | H8: AD-001-1-IN | I8: Instagram | J8: active | K8: 7-day click or 1-day view | L8: Lead generation | M8: Leads | N8: 0 | O8: 21.53 | P8: 3416 | Q8: 2913 | R8: 1.17 | S8: 28 | T8: 21 | U8: 0.82 | V8: 0.77 | W8: 6.3 | X8: 0 | Y8: 0 | Z8: Website Development | AA8: /services/website-development
A9: 2023-12-02 | B9: 2023-12-02 | C9: DA_Dec23_Website_Lead_Generation | D9: META-001 | E9: Startup Founders - Instagram | F9: AS-001-2 | G9: Lead Form Static | H9: AD-001-2-IN | I9: Instagram | J9: active | K9: 7-day click or 1-day view | L9: Lead generation | M9: Leads | N9: 0 | O9: 9.92 | P9: 1624 | Q9: 1362 | R9: 1.19 | S9: 24 | T9: 19 | U9: 1.48 | V9: 0.41 | W9: 6.11 | X9: 0 | Y9: 0 | Z9: Website Development | AA9: /services/website-development
A10: 2023-12-03 | B10: 2023-12-03 | C10: DA_Dec23_Website_Lead_Generation | D10: META-001 | E10: Small Business Owners - Facebook | F10: AS-001-1 | G10: Lead Form Static | H10: AD-001-1-FA | I10: Facebook | J10: active | K10: 7-day click or 1-day view | L10: Lead generation | M10: Leads | N10: 1 | O10: 25.25 | P10: 3543 | Q10: 2796 | R10: 1.27 | S10: 40 | T10: 32 | U10: 1.13 | V10: 0.63 | W10: 7.13 | X10: 1 | Y10: 25.25 | Z10: Website Development | AA10: /services/website-development
A11: 2023-12-03 | B11: 2023-12-03 | C11: DA_Dec23_Website_Lead_Generation | D11: META-001 | E11: Startup Founders - Facebook | F11: AS-001-2 | G11: Service Carousel | H11: AD-001-2-FA | I11: Facebook | J11: active | K11: 7-day click or 1-day view | L11: Lead generation | M11: Leads | N11: 1 | O11: 10.21 | P11: 1378 | Q11: 1141 | R11: 1.21 | S11: 24 | T11: 19 | U11: 1.74 | V11: 0.43 | W11: 7.41 | X11: 1 | Y11: 10.21 | Z11: Website Development | AA11: /services/website-development
A12: 2023-12-03 | B12: 2023-12-03 | C12: DA_Dec23_Website_Lead_Generation | D12: META-001 | E12: Small Business Owners - Instagram | F12: AS-001-1 | G12: Service Carousel | H12: AD-001-1-IN | I12: Instagram | J12: active | K12: 7-day click or 1-day view | L12: Lead generation | M12: Leads | N12: 0 | O12: 21.66 | P12: 2759 | Q12: 2418 | R12: 1.14 | S12: 25 | T12: 18 | U12: 0.91 | V12: 0.87 | W12: 7.85 | X12: 0 | Y12: 0 | Z12: Website Development | AA12: /services/website-development
A13: 2023-12-03 | B13: 2023-12-03 | C13: DA_Dec23_Website_Lead_Generation | D13: META-001 | E13: Startup Founders - Instagram | F13: AS-001-2 | G13: Lead Form Static | H13: AD-001-2-IN | I13: Instagram | J13: active | K13: 7-day click or 1-day view | L13: Lead generation | M13: Leads | N13: 0 | O13: 22.85 | P13: 4041 | Q13: 3370 | R13: 1.2 | S13: 37 | T13: 30 | U13: 0.92 | V13: 0.62 | W13: 5.65 | X13: 0 | Y13: 0 | Z13: Website Development | AA13: /services/website-development
... A1381: 2024-12-28 | B1381: 2024-12-28 | C1381: DA_Dec24_New_Year_Growth_Plan | D1381: META-013 | E1381: Startup Founders - Instagram | F1381: AS-013-2 | G1381: Service Carousel | H1381: AD-013-2-IN | I1381: Instagram | J1381: active | K1381: 7-day click or 1-day view | L1381: Lead generation | M1381: Leads | N1381: 1 | O1381: 21.46 | P1381: 3874 | Q1381: 3182 | R1381: 1.22 | S1381: 50 | T1381: 37 | U1381: 1.29 | V1381: 0.43 | W1381: 5.54 | X1381: 1 | Y1381: 21.46 | Z1381: Social Media Marketing | AA1381: /services/social-media-marketing

Sheet Raw_Google
A1: Day | B1: Campaign | C1: Campaign ID | D1: Ad group | E1: Ad group ID | F1: Keyword | G1: Match type | H1: Currency code | I1: Impressions | J1: Clicks | K1: CTR | L1: Avg. CPC | M1: Cost | N1: Conversions | O1: Cost / conv. | P1: Conv. rate | Q1: Search impr. share | R1: Service promoted | S1: Final URL
A2: 2023-12-01 | B2: Search_Dec23_Website_Lead_Generation | C2: GADS-001 | D2: Website Development - Core | E2: AG-001-1 | F2: website development company | G2: Phrase | H2: USD | I2: 310 | J2: 21 | K2: 6.77 | L2: 1.27 | M2: 26.65 | N2: 1 | O2: 26.65 | P2: 4.76 | Q2: 54% | R2: Website Development | S2: https://digiagent.example/services/website-development?utm_source=google&utm_medium=cpc
A3: 2023-12-01 | B3: Search_Dec23_Website_Lead_Generation | C3: GADS-001 | D3: Website Development - Competitor | E3: AG-001-2 | F3: business website design | G3: Exact | H3: USD | I3: 412 | J3: 24 | K3: 5.83 | L3: 0.93 | M3: 22.43 | N3: 2 | O3: 11.21 | P3: 8.33 | Q3: 65% | R3: Website Development | S3: https://digiagent.example/services/website-development?utm_source=google&utm_medium=cpc
A4: 2023-12-01 | B4: Search_Dec23_Website_Lead_Generation | C4: GADS-001 | D4: Website Development - Local | E4: AG-001-3 | F4: affordable website package | G4: Broad | H4: USD | I4: 413 | J4: 20 | K4: 4.84 | L4: 1.18 | M4: 23.6 | N4: 2 | O4: 11.8 | P4: 10 | Q4: 77% | R4: Website Development | S4: https://digiagent.example/services/website-development?utm_source=google&utm_medium=cpc
A5: 2023-12-02 | B5: Search_Dec23_Website_Lead_Generation | C5: GADS-001 | D5: Website Development - Core | E5: AG-001-1 | F5: website development company | G5: Phrase | H5: USD | I5: 958 | J5: 67 | K5: 6.99 | L5: 0.65 | M5: 43.28 | N5: 4 | O5: 10.82 | P5: 5.97 | Q5: 53% | R5: Website Development | S5: https://digiagent.example/services/website-development?utm_source=google&utm_medium=cpc
A6: 2023-12-02 | B6: Search_Dec23_Website_Lead_Generation | C6: GADS-001 | D6: Website Development - Competitor | E6: AG-001-2 | F6: business website design | G6: Exact | H6: USD | I6: 177 | J6: 13 | K6: 7.34 | L6: 1.02 | M6: 13.27 | N6: 1 | O6: 13.27 | P6: 7.69 | Q6: 43% | R6: Website Development | S6: https://digiagent.example/services/website-development?utm_source=google&utm_medium=cpc
A7: 2023-12-02 | B7: Search_Dec23_Website_Lead_Generation | C7: GADS-001 | D7: Website Development - Local | E7: AG-001-3 | F7: affordable website package | G7: Broad | H7: USD | I7: 415 | J7: 31 | K7: 7.47 | L7: 1.04 | M7: 32.2 | N7: 2 | O7: 16.1 | P7: 6.45 | Q7: 62% | R7: Website Development | S7: https://digiagent.example/services/website-development?utm_source=google&utm_medium=cpc
A8: 2023-12-03 | B8: Search_Dec23_Website_Lead_Generation | C8: GADS-001 | D8: Website Development - Core | E8: AG-001-1 | F8: website development company | G8: Phrase | H8: USD | I8: 895 | J8: 46 | K8: 5.14 | L8: 0.79 | M8: 36.33 | N8: 2 | O8: 18.16 | P8: 4.35 | Q8: 67% | R8: Website Development | S8: https://digiagent.example/services/website-development?utm_source=google&utm_medium=cpc
A9: 2023-12-03 | B9: Search_Dec23_Website_Lead_Generation | C9: GADS-001 | D9: Website Development - Competitor | E9: AG-001-2 | F9: business website design | G9: Exact | H9: USD | I9: 420 | J9: 29 | K9: 6.9 | L9: 0.72 | M9: 20.82 | N9: 2 | O9: 10.41 | P9: 6.9 | Q9: 50% | R9: Website Development | S9: https://digiagent.example/services/website-development?utm_source=google&utm_medium=cpc
A10: 2023-12-03 | B10: Search_Dec23_Website_Lead_Generation | C10: GADS-001 | D10: Website Development - Local | E10: AG-001-3 | F10: affordable website package | G10: Broad | H10: USD | I10: 375 | J10: 31 | K10: 8.27 | L10: 1.14 | M10: 35.47 | N10: 2 | O10: 17.73 | P10: 6.45 | Q10: 60% | R10: Website Development | S10: https://digiagent.example/services/website-development?utm_source=google&utm_medium=cpc
A11: 2023-12-04 | B11: Search_Dec23_Website_Lead_Generation | C11: GADS-001 | D11: Website Development - Core | E11: AG-001-1 | F11: website development company | G11: Phrase | H11: USD | I11: 922 | J11: 43 | K11: 4.66 | L11: 1.22 | M11: 52.41 | N11: 4 | O11: 13.1 | P11: 9.3 | Q11: 71% | R11: Website Development | S11: https://digiagent.example/services/website-development?utm_source=google&utm_medium=cpc
A12: 2023-12-04 | B12: Search_Dec23_Website_Lead_Generation | C12: GADS-001 | D12: Website Development - Competitor | E12: AG-001-2 | F12: business website design | G12: Exact | H12: USD | I12: 159 | J12: 13 | K12: 8.18 | L12: 1.26 | M12: 16.42 | N12: 1 | O12: 16.42 | P12: 7.69 | Q12: 57% | R12: Website Development | S12: https://digiagent.example/services/website-development?utm_source=google&utm_medium=cpc
A13: 2023-12-04 | B13: Search_Dec23_Website_Lead_Generation | C13: GADS-001 | D13: Website Development - Local | E13: AG-001-3 | F13: affordable website package | G13: Broad | H13: USD | I13: 447 | J13: 31 | K13: 6.94 | L13: 1.21 | M13: 37.39 | N13: 1 | O13: 37.39 | P13: 3.23 | Q13: 76% | R13: Website Development | S13: https://digiagent.example/services/website-development?utm_source=google&utm_medium=cpc
... A1036: 2024-12-28 | B1036: Search_Dec24_New_Year_Growth_Plan | C1036: GADS-013 | D1036: Social Media Marketing - Local | E1036: AG-013-3 | F1036: instagram marketing package | G1036: Broad | H1036: USD | I1036: 696 | J1036: 51 | K1036: 7.33 | L1036: 0.52 | M1036: 26.43 | N1036: 5 | O1036: 5.29 | P1036: 9.8 | Q1036: 42% | R1036: Social Media Marketing | S1036: https://digiagent.example/services/social-media-marketing?utm_source=google&utm_medium=cpc

Sheet Raw_Website
A1: Date | B1: Session source / medium | C1: Default channel group | D1: Campaign | E1: Landing page + query string | F1: Users | G1: Sessions | H1: Engaged sessions | I1: Engagement rate | J1: Bounce rate | K1: Average session duration | L1: New users | M1: Key events | N1: Form submissions | O1: Service interest
A2: 2023-12-01 | B2: google / organic | C2: Organic Search | D2: (organic) | E2: /services/website-development | F2: 65 | G2: 88 | H2: 44 | I2: 50 | J2: 50 | K2: 119 | L2: 42 | M2: 4 | N2: 1 | O2: Website Development
A3: 2023-12-01 | B3: direct / none | C3: Direct | D3: (direct) | E3: /services/seo | F3: 29 | G3: 37 | H3: 18 | I3: 48.65 | J3: 51.35 | K3: 133 | L3: 16 | M3: 1 | N3: 0 | O3: SEO Services
A4: 2023-12-01 | B4: facebook.com / referral | C4: Referral | D4: (referral) | E4: /services/branding | F4: 13 | G4: 18 | H4: 12 | I4: 66.67 | J4: 33.33 | K4: 93 | L4: 8 | M4: 0 | N4: 0 | O4: Branding & Design
A5: 2023-12-01 | B5: instagram.com / referral | C5: Referral | D5: (referral) | E5: /services/social-media-marketing | F5: 8 | G5: 11 | H5: 5 | I5: 45.45 | J5: 54.55 | K5: 113 | L5: 4 | M5: 0 | N5: 0 | O5: Social Media Marketing
A6: 2023-12-01 | B6: linkedin.com / referral | C6: Referral | D6: (referral) | E6: /services/branding | F6: 14 | G6: 18 | H6: 8 | I6: 44.44 | J6: 55.56 | K6: 54 | L6: 8 | M6: 0 | N6: 0 | O6: Branding & Design
A7: 2023-12-01 | B7: google / cpc | C7: Paid Search | D7: Search_Dec23_Website_Lead_Generation | E7: /services/website-development?utm_campaign=Search_Dec23_Website_Lead_Generation | F7: 56 | G7: 60 | H7: 31 | I7: 51.67 | J7: 48.33 | K7: 179 | L7: 34 | M7: 2 | N7: 1 | O7: Website Development
A8: 2023-12-01 | B8: facebook / paid_social | C8: Paid Social | D8: DA_Dec23_Website_Lead_Generation | E8: /services/website-development?utm_campaign=DA_Dec23_Website_Lead_Generation | F8: 42 | G8: 57 | H8: 38 | I8: 66.67 | J8: 33.33 | K8: 159 | L8: 23 | M8: 3 | N8: 1 | O8: Website Development
A9: 2023-12-01 | B9: instagram / paid_social | C9: Paid Social | D9: DA_Dec23_Website_Lead_Generation | E9: /services/website-development?utm_campaign=DA_Dec23_Website_Lead_Generation | F9: 24 | G9: 33 | H9: 21 | I9: 63.64 | J9: 36.36 | K9: 150 | L9: 13 | M9: 1 | N9: 0 | O9: Website Development
A10: 2023-12-01 | B10: newsletter / email | C10: Email | D10: newsletter | E10: /services/website-development?utm_campaign=newsletter | F10: 10 | G10: 14 | H10: 6 | I10: 42.86 | J10: 57.14 | K10: 64 | L10: 6 | M10: 0 | N10: 0 | O10: Website Development
A11: 2023-12-02 | B11: google / organic | C11: Organic Search | D11: (organic) | E11: /services/website-development | F11: 63 | G11: 81 | H11: 45 | I11: 55.56 | J11: 44.44 | K11: 89 | L11: 42 | M11: 3 | N11: 2 | O11: Website Development
A12: 2023-12-02 | B12: direct / none | C12: Direct | D12: (direct) | E12: /services/ecommerce-store | F12: 22 | G12: 27 | H12: 17 | I12: 62.96 | J12: 37.04 | K12: 105 | L12: 14 | M12: 0 | N12: 0 | O12: eCommerce Website
A13: 2023-12-02 | B13: facebook.com / referral | C13: Referral | D13: (referral) | E13: /services/website-development | F13: 38 | G13: 42 | H13: 28 | I13: 66.67 | J13: 33.33 | K13: 124 | L13: 28 | M13: 0 | N13: 0 | O13: Website Development
... A3574: 2024-12-31 | B3574: newsletter / email | C3574: Email | D3574: newsletter | E3574: /services/social-media-marketing?utm_campaign=newsletter | F3574: 5 | G3574: 6 | H3574: 3 | I3574: 50 | J3574: 50 | K3574: 140 | L3574: 3 | M3574: 0 | N3574: 0 | O3574: Social Media Marketing

Sheet Raw_Email
A1: Send date | B1: Email campaign name | C1: Audience/list | D1: Subject line | E1: UTM campaign | F1: Emails sent | G1: Delivered | H1: Delivery rate | I1: Unique opens | J1: Open rate | K1: Unique clicks | L1: Click rate | M1: Bounces | N1: Unsubscribes | O1: Leads | P1: Estimated tool/design cost (USD) | Q1: Service promoted
A2: 2023-12-11 | B2: Email_Dec23_Website_Lead_Generation_educational_nurture | C2: Digi Agent Prospect List | D2: Website Development ideas for growing businesses | E2: Dec23_Website_Lead_Generation | F2: 1633 | G2: 1597 | H2: 97.8 | I2: 340 | J2: 21.29 | K2: 99 | L2: 6.2 | M2: 36 | N2: 7 | O2: 9 | P2: 28.61 | Q2: Website Development
A3: 2023-12-22 | B3: Email_Dec23_Website_Lead_Generation_offer_reminder | C3: Digi Agent Prospect List | D3: Website Development ideas for growing businesses | E3: Dec23_Website_Lead_Generation | F3: 1276 | G3: 1245 | H3: 97.57 | I3: 372 | J3: 29.88 | K3: 59 | L3: 4.74 | M3: 31 | N3: 5 | O3: 8 | P3: 33.43 | Q3: Website Development
A4: 2024-01-11 | B4: Email_Jan24_eCommerce_Growth_Push_educational_nurture | C4: Digi Agent Prospect List | D4: eCommerce Website ideas for growing businesses | E4: Jan24_eCommerce_Growth_Push | F4: 1145 | G4: 1108 | H4: 96.77 | I4: 238 | J4: 21.48 | K4: 82 | L4: 7.4 | M4: 37 | N4: 7 | O4: 6 | P4: 35.48 | Q4: eCommerce Website
A5: 2024-01-22 | B5: Email_Jan24_eCommerce_Growth_Push_offer_reminder | C5: Digi Agent Prospect List | D5: eCommerce Website ideas for growing businesses | E5: Jan24_eCommerce_Growth_Push | F5: 1046 | G5: 1021 | H5: 97.61 | I5: 232 | J5: 22.72 | K5: 32 | L5: 3.13 | M5: 25 | N5: 4 | O5: 5 | P5: 20.17 | Q5: eCommerce Website
A6: 2024-02-11 | B6: Email_Feb24_Social_Media_Audit_educational_nurture | C6: Digi Agent Prospect List | D6: Social Media Marketing ideas for growing businesses | E6: Feb24_Social_Media_Audit | F6: 1428 | G6: 1390 | H6: 97.34 | I6: 316 | J6: 22.73 | K6: 60 | L6: 4.32 | M6: 38 | N6: 6 | O6: 7 | P6: 35.38 | Q6: Social Media Marketing
A7: 2024-02-22 | B7: Email_Feb24_Social_Media_Audit_offer_reminder | C7: Digi Agent Prospect List | D7: Social Media Marketing ideas for growing businesses | E7: Feb24_Social_Media_Audit | F7: 895 | G7: 878 | H7: 98.1 | I7: 171 | J7: 19.48 | K7: 32 | L7: 3.64 | M7: 17 | N7: 5 | O7: 3 | P7: 31.75 | Q7: Social Media Marketing
A8: 2024-03-11 | B8: Email_Mar24_Startup_Branding_Offer_educational_nurture | C8: Digi Agent Prospect List | D8: Branding & Design ideas for growing businesses | E8: Mar24_Startup_Branding_Offer | F8: 1581 | G8: 1535 | H8: 97.09 | I8: 498 | J8: 32.44 | K8: 54 | L8: 3.52 | M8: 46 | N8: 6 | O8: 5 | P8: 34.89 | Q8: Branding & Design
A9: 2024-03-22 | B9: Email_Mar24_Startup_Branding_Offer_offer_reminder | C9: Digi Agent Prospect List | D9: Branding & Design ideas for growing businesses | E9: Mar24_Startup_Branding_Offer | F9: 1011 | G9: 995 | H9: 98.42 | I9: 275 | J9: 27.64 | K9: 49 | L9: 4.92 | M9: 16 | N9: 1 | O9: 8 | P9: 37.66 | Q9: Branding & Design
A10: 2024-04-11 | B10: Email_Apr24_Website_Redesign_Leads_educational_nurture | C10: Digi Agent Prospect List | D10: Website Development ideas for growing businesses | E10: Apr24_Website_Redesign_Leads | F10: 1458 | G10: 1407 | H10: 96.5 | I10: 403 | J10: 28.64 | K10: 68 | L10: 4.83 | M10: 51 | N10: 8 | O10: 7 | P10: 29.49 | Q10: Website Development
A11: 2024-04-22 | B11: Email_Apr24_Website_Redesign_Leads_offer_reminder | C11: Digi Agent Prospect List | D11: Website Development ideas for growing businesses | E11: Apr24_Website_Redesign_Leads | F11: 1406 | G11: 1375 | H11: 97.8 | I11: 350 | J11: 25.45 | K11: 102 | L11: 7.42 | M11: 31 | N11: 3 | O11: 10 | P11: 25.54 | Q11: Website Development
A12: 2024-05-11 | B12: Email_May24_SEO_Audit_Campaign_educational_nurture | C12: Digi Agent Prospect List | D12: SEO Services ideas for growing businesses | E12: May24_SEO_Audit_Campaign | F12: 1451 | G12: 1437 | H12: 99.04 | I12: 264 | J12: 18.37 | K12: 81 | L12: 5.64 | M12: 14 | N12: 4 | O12: 8 | P12: 30.23 | Q12: SEO Services
A13: 2024-05-22 | B13: Email_May24_SEO_Audit_Campaign_offer_reminder | C13: Digi Agent Prospect List | D13: SEO Services ideas for growing businesses | E13: May24_SEO_Audit_Campaign | F13: 1316 | G13: 1298 | H13: 98.63 | I13: 328 | J13: 25.27 | K13: 81 | L13: 6.24 | M13: 18 | N13: 7 | O13: 12 | P13: 30.08 | Q13: SEO Services
... A27: 2024-12-22 | B27: Email_Dec24_New_Year_Growth_Plan_offer_reminder | C27: Digi Agent Prospect List | D27: Social Media Marketing ideas for growing businesses | E27: Dec24_New_Year_Growth_Plan | F27: 1534 | G27: 1509 | H27: 98.37 | I27: 385 | J27: 25.51 | K27: 98 | L27: 6.49 | M27: 25 | N27: 5 | O27: 16 | P27: 33.14 | Q27: Social Media Marketing

Sheet Raw_CRM
A1: Lead ID | B1: Created date | C1: Lead source | D1: Platform / medium | E1: Campaign name | F1: Service interested | G1: Lead status | H1: Qualified lead | I1: Lead quality score | J1: Estimated deal value (USD) | K1: Converted customer | L1: Revenue (USD) | M1: Closed date | N1: Sales notes
A2: L10001 | B2: 2023-12-01 | C2: Facebook Ads | D2: Facebook | E2: DA_Dec23_Website_Lead_Generation | F2: Website Development | G2: Lost | H2: No | I2: 27 | J2: 1978.66 | K2: No | L2: 0 | N2: Budget too low
A3: L10002 | B3: 2023-12-01 | C3: Facebook Ads | D3: Facebook | E3: DA_Dec23_Website_Lead_Generation | F3: Website Development | G3: Unqualified | H3: No | I3: 59 | J3: 0 | K3: No | L3: 0 | N3: No response after first contact
A4: L10003 | B4: 2023-12-01 | C4: Facebook Ads | D4: Facebook | E4: DA_Dec23_Website_Lead_Generation | F4: Website Development | G4: Unqualified | H4: No | I4: 23 | J4: 0 | K4: No | L4: 0 | N4: Budget too low
A5: L10004 | B5: 2023-12-01 | C5: Facebook Ads | D5: Facebook | E5: DA_Dec23_Website_Lead_Generation | F5: Website Development | G5: Unqualified | H5: No | I5: 53 | J5: 0 | K5: No | L5: 0 | N5: Information request only
A6: L10005 | B6: 2023-12-01 | C6: Facebook Ads | D6: Facebook | E6: DA_Dec23_Website_Lead_Generation | F6: Website Development | G6: Lost | H6: No | I6: 57 | J6: 834.23 | K6: No | L6: 0 | N6: Outside target segment
A7: L10006 | B7: 2023-12-01 | C7: Instagram Ads | D7: Instagram | E7: DA_Dec23_Website_Lead_Generation | F7: Website Development | G7: Qualified | H7: Yes | I7: 83 | J7: 2304 | K7: No | L7: 0 | N7: Qualified but not closed yet
A8: L10007 | B8: 2023-12-01 | C8: Instagram Ads | D8: Instagram | E8: DA_Dec23_Website_Lead_Generation | F8: Website Development | G8: Qualified | H8: Yes | I8: 73 | J8: 2969.86 | K8: No | L8: 0 | N8: Qualified but not closed yet
A9: L10008 | B9: 2023-12-02 | C9: Facebook Ads | D9: Facebook | E9: DA_Dec23_Website_Lead_Generation | F9: Website Development | G9: Contacted | H9: No | I9: 44 | J9: 662.55 | K9: No | L9: 0 | N9: Information request only
A10: L10009 | B10: 2023-12-02 | C10: Facebook Ads | D10: Facebook | E10: DA_Dec23_Website_Lead_Generation | F10: Website Development | G10: Lost | H10: No | I10: 47 | J10: 1332.93 | K10: No | L10: 0 | N10: Budget too low
A11: L10010 | B11: 2023-12-03 | C11: Facebook Ads | D11: Facebook | E11: DA_Dec23_Website_Lead_Generation | F11: Website Development | G11: Unqualified | H11: No | I11: 39 | J11: 0 | K11: No | L11: 0 | N11: Outside target segment
A12: L10011 | B12: 2023-12-03 | C12: Facebook Ads | D12: Facebook | E12: DA_Dec23_Website_Lead_Generation | F12: Website Development | G12: Contacted | H12: Yes | I12: 81 | J12: 1775.87 | K12: No | L12: 0 | N12: Needs follow-up
A13: L10012 | B13: 2023-12-04 | C13: Facebook Ads | D13: Facebook | E13: DA_Dec23_Website_Lead_Generation | F13: Website Development | G13: Proposal Sent | H13: Yes | I13: 95 | J13: 2171.88 | K13: No | L13: 0 | N13: Qualified but not closed yet
... A25: L10024 | B25: 2023-12-07 | C25: Facebook Ads | D25: Facebook | E25: DA_Dec23_Website_Lead_Generation | F25: Website Development | G25: Contacted | H25: Yes | I25: 80 | J25: 2895.24 | K25: No | L25: 0 | N25: Needs follow-up
A26: L10025 | B26: 2023-12-07 | C26: Facebook Ads | D26: Facebook | E26: DA_Dec23_Website_Lead_Generation | F26: Website Development | G26: Won | H26: Yes | I26: 62 | J26: 2612.11 | K26: Yes | L26: 1991.75 | M26: 2023-12-26 | N26: Converted after proposal follow-up
A27: L10026 | B27: 2023-12-07 | C27: Facebook Ads | D27: Facebook | E27: DA_Dec23_Website_Lead_Generation | F27: Website Development | G27: Lost | H27: No | I27: 26 | J27: 1418.62 | K27: No | L27: 0 | N27: Information request only
A28: L10027 | B28: 2023-12-07 | C28: Facebook Ads | D28: Facebook | E28: DA_Dec23_Website_Lead_Generation | F28: Website Development | G28: Lost | H28: No | I28: 59 | J28: 994.94 | K28: No | L28: 0 | N28: Budget too low
A29: L10028 | B29: 2023-12-07 | C29: Facebook Ads | D29: Facebook | E29: DA_Dec23_Website_Lead_Generation | F29: Website Development | G29: Lost | H29: No | I29: 38 | J29: 2110.34 | K29: No | L29: 0 | N29: Information request only
A30: L10029 | B30: 2023-12-07 | C30: Instagram Ads | D30: Instagram | E30: DA_Dec23_Website_Lead_Generation | F30: Website Development | G30: Lost | H30: No | I30: 43 | J30: 1657.48 | K30: No | L30: 0 | N30: Information request only
A31: L10030 | B31: 2023-12-08 | C31: Facebook Ads | D31: Facebook | E31: DA_Dec23_Website_Lead_Generation | F31: Website Development | G31: Lost | H31: No | I31: 49 | J31: 1524.05 | K31: No | L31: 0 | N31: Outside target segment
A32: L10031 | B32: 2023-12-08 | C32: Facebook Ads | D32: Facebook | E32: DA_Dec23_Website_Lead_Generation | F32: Website Development | G32: Unqualified | H32: No | I32: 38 | J32: 0 | K32: No | L32: 0 | N32: No response after first contact
A33: L10032 | B33: 2023-12-08 | C33: Facebook Ads | D33: Facebook | E33: DA_Dec23_Website_Lead_Generation | F33: Website Development | G33: Contacted | H33: No | I33: 41 | J33: 1728.03 | K33: No | L33: 0 | N33: Information request only
A34: L10033 | B34: 2023-12-08 | C34: Instagram Ads | D34: Instagram | E34: DA_Dec23_Website_Lead_Generation | F34: Website Development | G34: Qualified | H34: Yes | I34: 83 | J34: 2974 | K34: No | L34: 0 | N34: Qualified but not closed yet
A35: L10034 | B35: 2023-12-09 | C35: Facebook Ads | D35: Facebook | E35: DA_Dec23_Website_Lead_Generation | F35: Website Development | G35: Lost | H35: No | I35: 58 | J35: 1234.04 | K35: No | L35: 0 | N35: No response after first contact
A36: L10035 | B36: 2023-12-09 | C36: Facebook Ads | D36: Facebook | E36: DA_Dec23_Website_Lead_Generation | F36: Website Development | G36: Qualified | H36: Yes | I36: 82 | J36: 2347.77 | K36: No | L36: 0 | N36: Qualified but not closed yet
A37: L10036 | B37: 2023-12-09 | C37: Facebook Ads | D37: Facebook | E37: DA_Dec23_Website_Lead_Generation | F37: Website Development | G37: Qualified | H37: Yes | I37: 72 | J37: 2663.86 | K37: No | L37: 0 | N37: Qualified but not closed yet
A38: L10037 | B38: 2023-12-10 | C38: Facebook Ads | D38: Facebook | E38: DA_Dec23_Website_Lead_Generation | F38: Website Development | G38: Unqualified | H38: No | I38: 48 | J38: 0 | K38: No | L38: 0 | N38: Budget too low
... A51: L10050 | B51: 2023-12-12 | C51: Facebook Ads | D51: Facebook | E51: DA_Dec23_Website_Lead_Generation | F51: Website Development | G51: Unqualified | H51: No | I51: 39 | J51: 0 | K51: No | L51: 0 | N51: Information request only
A52: L10051 | B52: 2023-12-12 | C52: Facebook Ads | D52: Facebook | E52: DA_Dec23_Website_Lead_Generation | F52: Website Development | G52: Won | H52: Yes | I52: 80 | J52: 2582.02 | K52: Yes | L52: 2499.08 | M52: 2024-01-07 | N52: Converted after proposal follow-up
A53: L10052 | B53: 2023-12-12 | C53: Facebook Ads | D53: Facebook | E53: DA_Dec23_Website_Lead_Generation | F53: Website Development | G53: Lost | H53: No | I53: 31 | J53: 660.07 | K53: No | L53: 0 | N53: Information request only
A54: L10053 | B54: 2023-12-12 | C54: Facebook Ads | D54: Facebook | E54: DA_Dec23_Website_Lead_Generation | F54: Website Development | G54: Proposal Sent | H54: Yes | I54: 62 | J54: 2989.53 | K54: No | L54: 0 | N54: Qualified but not closed yet
A55: L10054 | B55: 2023-12-12 | C55: Instagram Ads | D55: Instagram | E55: DA_Dec23_Website_Lead_Generation | F55: Website Development | G55: Lost | H55: No | I55: 49 | J55: 1804.97 | K55: No | L55: 0 | N55: No response after first contact
A56: L10055 | B56: 2023-12-12 | C56: Instagram Ads | D56: Instagram | E56: DA_Dec23_Website_Lead_Generation | F56: Website Development | G56: Contacted | H56: Yes | I56: 85 | J56: 2388.95 | K56: No | L56: 0 | N56: Needs follow-up
A57: L10056 | B57: 2023-12-13 | C57: Facebook Ads | D57: Facebook | E57: DA_Dec23_Website_Lead_Generation | F57: Website Development | G57: Unqualified | H57: No | I57: 49 | J57: 0 | K57: No | L57: 0 | N57: Outside target segment
A58: L10057 | B58: 2023-12-13 | C58: Facebook Ads | D58: Facebook | E58: DA_Dec23_Website_Lead_Generation | F58: Website Development | G58: Lost | H58: No | I58: 20 | J58: 1581.01 | K58: No | L58: 0 | N58: Budget too low
A59: L10058 | B59: 2023-12-13 | C59: Instagram Ads | D59: Instagram | E59: DA_Dec23_Website_Lead_Generation | F59: Website Development | G59: Unqualified | H59: No | I59: 23 | J59: 0 | K59: No | L59: 0 | N59: Budget too low
A60: L10059 | B60: 2023-12-13 | C60: Instagram Ads | D60: Instagram | E60: DA_Dec23_Website_Lead_Generation | F60: Website Development | G60: Lost | H60: No | I60: 42 | J60: 1921.68 | K60: No | L60: 0 | N60: Information request only
A61: L10060 | B61: 2023-12-14 | C61: Facebook Ads | D61: Facebook | E61: DA_Dec23_Website_Lead_Generation | F61: Website Development | G61: Qualified | H61: Yes | I61: 78 | J61: 2372.91 | K61: No | L61: 0 | N61: Qualified but not closed yet
A62: L10061 | B62: 2023-12-14 | C62: Facebook Ads | D62: Facebook | E62: DA_Dec23_Website_Lead_Generation | F62: Website Development | G62: Unqualified | H62: No | I62: 29 | J62: 0 | K62: No | L62: 0 | N62: Information request only
A63: L10062 | B63: 2023-12-14 | C63: Facebook Ads | D63: Facebook | E63: DA_Dec23_Website_Lead_Generation | F63: Website Development | G63: Qualified | H63: Yes | I63: 78 | J63: 2480.37 | K63: No | L63: 0 | N63: Qualified but not closed yet
A64: L10063 | B64: 2023-12-14 | C64: Facebook Ads | D64: Facebook | E64: DA_Dec23_Website_Lead_Generation | F64: Website Development | G64: Contacted | H64: Yes | I64: 83 | J64: 2189.21 | K64: No | L64: 0 | N64: Needs follow-up
... A67: L10066 | B67: 2023-12-15 | C67: Instagram Ads | D67: Instagram | E67: DA_Dec23_Website_Lead_Generation | F67: Website Development | G67: Lost | H67: No | I67: 43 | J67: 1961.28 | K67: No | L67: 0 | N67: Information request only
A68: L10067 | B68: 2023-12-16 | C68: Facebook Ads | D68: Facebook | E68: DA_Dec23_Website_Lead_Generation | F68: Website Development | G68: Won | H68: Yes | I68: 92 | J68: 2576.25 | K68: Yes | L68: 1754.64 | M68: 2024-01-22 | N68: Converted after proposal follow-up
A69: L10068 | B69: 2023-12-16 | C69: Facebook Ads | D69: Facebook | E69: DA_Dec23_Website_Lead_Generation | F69: Website Development | G69: Contacted | H69: No | I69: 23 | J69: 2089.7 | K69: No | L69: 0 | N69: Outside target segment
A70: L10069 | B70: 2023-12-17 | C70: Facebook Ads | D70: Facebook | E70: DA_Dec23_Website_Lead_Generation | F70: Website Development | G70: Unqualified | H70: No | I70: 30 | J70: 0 | K70: No | L70: 0 | N70: No response after first contact
A71: L10070 | B71: 2023-12-17 | C71: Facebook Ads | D71: Facebook | E71: DA_Dec23_Website_Lead_Generation | F71: Website Development | G71: Contacted | H71: Yes | I71: 95 | J71: 1956.9 | K71: No | L71: 0 | N71: Needs follow-up
A72: L10071 | B72: 2023-12-18 | C72: Facebook Ads | D72: Facebook | E72: DA_Dec23_Website_Lead_Generation | F72: Website Development | G72: Lost | H72: No | I72: 57 | J72: 1175.54 | K72: No | L72: 0 | N72: Information request only
A73: L10072 | B73: 2023-12-18 | C73: Facebook Ads | D73: Facebook | E73: DA_Dec23_Website_Lead_Generation | F73: Website Development | G73: Lost | H73: No | I73: 56 | J73: 649.58 | K73: No | L73: 0 | N73: Outside target segment
A74: L10073 | B74: 2023-12-18 | C74: Facebook Ads | D74: Facebook | E74: DA_Dec23_Website_Lead_Generation | F74: Website Development | G74: Contacted | H74: No | I74: 46 | J74: 1103.06 | K74: No | L74: 0 | N74: Information request only
A75: L10074 | B75: 2023-12-18 | C75: Facebook Ads | D75: Facebook | E75: DA_Dec23_Website_Lead_Generation | F75: Website Development | G75: Unqualified | H75: No | I75: 29 | J75: 0 | K75: No | L75: 0 | N75: Budget too low
A76: L10075 | B76: 2023-12-18 | C76: Facebook Ads | D76: Facebook | E76: DA_Dec23_Website_Lead_Generation | F76: Website Development | G76: Lost | H76: No | I76: 25 | J76: 1762.88 | K76: No | L76: 0 | N76: No response after first contact
A77: L10076 | B77: 2023-12-18 | C77: Instagram Ads | D77: Instagram | E77: DA_Dec23_Website_Lead_Generation | F77: Website Development | G77: Proposal Sent | H77: Yes | I77: 75 | J77: 2277.55 | K77: No | L77: 0 | N77: Qualified but not closed yet
A78: L10077 | B78: 2023-12-19 | C78: Facebook Ads | D78: Facebook | E78: DA_Dec23_Website_Lead_Generation | F78: Website Development | G78: Lost | H78: No | I78: 60 | J78: 1361.31 | K78: No | L78: 0 | N78: Budget too low
A79: L10078 | B79: 2023-12-19 | C79: Facebook Ads | D79: Facebook | E79: DA_Dec23_Website_Lead_Generation | F79: Website Development | G79: Contacted | H79: No | I79: 23 | J79: 1278.34 | K79: No | L79: 0 | N79: Information request only
A80: L10079 | B80: 2023-12-19 | C80: Facebook Ads | D80: Facebook | E80: DA_Dec23_Website_Lead_Generation | F80: Website Development | G80: Lost | H80: No | I80: 51 | J80: 1213.89 | K80: No | L80: 0 | N80: No response after first contact
... A84: L10083 | B84: 2023-12-21 | C84: Facebook Ads | D84: Facebook | E84: DA_Dec23_Website_Lead_Generation | F84: Website Development | G84: Lost | H84: No | I84: 33 | J84: 1010.99 | K84: No | L84: 0 | N84: Budget too low
A85: L10084 | B85: 2023-12-21 | C85: Facebook Ads | D85: Facebook | E85: DA_Dec23_Website_Lead_Generation | F85: Website Development | G85: Won | H85: Yes | I85: 90 | J85: 2982.36 | K85: Yes | L85: 2312.13 | M85: 2024-01-08 | N85: Converted after proposal follow-up
A86: L10085 | B86: 2023-12-21 | C86: Facebook Ads | D86: Facebook | E86: DA_Dec23_Website_Lead_Generation | F86: Website Development | G86: Unqualified | H86: No | I86: 26 | J86: 0 | K86: No | L86: 0 | N86: Budget too low
A87: L10086 | B87: 2023-12-21 | C87: Facebook Ads | D87: Facebook | E87: DA_Dec23_Website_Lead_Generation | F87: Website Development | G87: Proposal Sent | H87: Yes | I87: 96 | J87: 1907.83 | K87: No | L87: 0 | N87: Qualified but not closed yet
A88: L10087 | B88: 2023-12-21 | C88: Facebook Ads | D88: Facebook | E88: DA_Dec23_Website_Lead_Generation | F88: Website Development | G88: Proposal Sent | H88: Yes | I88: 88 | J88: 2390.76 | K88: No | L88: 0 | N88: Qualified but not closed yet
A89: L10088 | B89: 2023-12-21 | C89: Facebook Ads | D89: Facebook | E89: DA_Dec23_Website_Lead_Generation | F89: Website Development | G89: Contacted | H89: Yes | I89: 66 | J89: 2764.09 | K89: No | L89: 0 | N89: Needs follow-up
A90: L10089 | B90: 2023-12-21 | C90: Instagram Ads | D90: Instagram | E90: DA_Dec23_Website_Lead_Generation | F90: Website Development | G90: Qualified | H90: Yes | I90: 81 | J90: 2353.18 | K90: No | L90: 0 | N90: Qualified but not closed yet
A91: L10090 | B91: 2023-12-22 | C91: Facebook Ads | D91: Facebook | E91: DA_Dec23_Website_Lead_Generation | F91: Website Development | G91: Unqualified | H91: No | I91: 48 | J91: 0 | K91: No | L91: 0 | N91: Budget too low
A92: L10091 | B92: 2023-12-22 | C92: Facebook Ads | D92: Facebook | E92: DA_Dec23_Website_Lead_Generation | F92: Website Development | G92: Lost | H92: No | I92: 20 | J92: 661.23 | K92: No | L92: 0 | N92: No response after first contact
A93: L10092 | B93: 2023-12-23 | C93: Facebook Ads | D93: Facebook | E93: DA_Dec23_Website_Lead_Generation | F93: Website Development | G93: Unqualified | H93: No | I93: 44 | J93: 0 | K93: No | L93: 0 | N93: Outside target segment
A94: L10093 | B94: 2023-12-23 | C94: Facebook Ads | D94: Facebook | E94: DA_Dec23_Website_Lead_Generation | F94: Website Development | G94: Unqualified | H94: No | I94: 53 | J94: 0 | K94: No | L94: 0 | N94: Budget too low
A95: L10094 | B95: 2023-12-23 | C95: Facebook Ads | D95: Facebook | E95: DA_Dec23_Website_Lead_Generation | F95: Website Development | G95: Unqualified | H95: No | I95: 50 | J95: 0 | K95: No | L95: 0 | N95: No response after first contact
A96: L10095 | B96: 2023-12-23 | C96: Instagram Ads | D96: Instagram | E96: DA_Dec23_Website_Lead_Generation | F96: Website Development | G96: Lost | H96: No | I96: 58 | J96: 1447.85 | K96: No | L96: 0 | N96: Budget too low
A97: L10096 | B97: 2023-12-24 | C97: Facebook Ads | D97: Facebook | E97: DA_Dec23_Website_Lead_Generation | F97: Website Development | G97: Contacted | H97: No | I97: 20 | J97: 1241.98 | K97: No | L97: 0 | N97: Information request only
... A102: L10101 | B102: 2023-12-24 | C102: Instagram Ads | D102: Instagram | E102: DA_Dec23_Website_Lead_Generation | F102: Website Development | G102: Lost | H102: No | I102: 51 | J102: 1368.08 | K102: No | L102: 0 | N102: Budget too low
A103: L10102 | B103: 2023-12-24 | C103: Instagram Ads | D103: Instagram | E103: DA_Dec23_Website_Lead_Generation | F103: Website Development | G103: Won | H103: Yes | I103: 68 | J103: 1888.15 | K103: Yes | L103: 2204.98 | M103: 2024-02-02 | N103: Converted after proposal follow-up
A104: L10103 | B104: 2023-12-25 | C104: Facebook Ads | D104: Facebook | E104: DA_Dec23_Website_Lead_Generation | F104: Website Development | G104: Unqualified | H104: No | I104: 25 | J104: 0 | K104: No | L104: 0 | N104: No response after first contact
A105: L10104 | B105: 2023-12-25 | C105: Facebook Ads | D105: Facebook | E105: DA_Dec23_Website_Lead_Generation | F105: Website Development | G105: Lost | H105: No | I105: 27 | J105: 1092.73 | K105: No | L105: 0 | N105: Information request only
A106: L10105 | B106: 2023-12-25 | C106: Facebook Ads | D106: Facebook | E106: DA_Dec23_Website_Lead_Generation | F106: Website Development | G106: Unqualified | H106: No | I106: 53 | J106: 0 | K106: No | L106: 0 | N106: Information request only
A107: L10106 | B107: 2023-12-25 | C107: Facebook Ads | D107: Facebook | E107: DA_Dec23_Website_Lead_Generation | F107: Website Development | G107: Unqualified | H107: No | I107: 45 | J107: 0 | K107: No | L107: 0 | N107: No response after first contact
A108: L10107 | B108: 2023-12-25 | C108: Instagram Ads | D108: Instagram | E108: DA_Dec23_Website_Lead_Generation | F108: Website Development | G108: Proposal Sent | H108: Yes | I108: 68 | J108: 2499.38 | K108: No | L108: 0 | N108: Qualified but not closed yet
A109: L10108 | B109: 2023-12-26 | C109: Facebook Ads | D109: Facebook | E109: DA_Dec23_Website_Lead_Generation | F109: Website Development | G109: Contacted | H109: No | I109: 36 | J109: 1293.57 | K109: No | L109: 0 | N109: Budget too low
A110: L10109 | B110: 2023-12-26 | C110: Facebook Ads | D110: Facebook | E110: DA_Dec23_Website_Lead_Generation | F110: Website Development | G110: Lost | H110: No | I110: 29 | J110: 1319.2 | K110: No | L110: 0 | N110: No response after first contact
A111: L10110 | B111: 2023-12-26 | C111: Facebook Ads | D111: Facebook | E111: DA_Dec23_Website_Lead_Generation | F111: Website Development | G111: Unqualified | H111: No | I111: 47 | J111: 0 | K111: No | L111: 0 | N111: No response after first contact
A112: L10111 | B112: 2023-12-26 | C112: Facebook Ads | D112: Facebook | E112: DA_Dec23_Website_Lead_Generation | F112: Website Development | G112: Lost | H112: No | I112: 50 | J112: 1954.36 | K112: No | L112: 0 | N112: Budget too low
A113: L10112 | B113: 2023-12-26 | C113: Facebook Ads | D113: Facebook | E113: DA_Dec23_Website_Lead_Generation | F113: Website Development | G113: Contacted | H113: No | I113: 22 | J113: 727.41 | K113: No | L113: 0 | N113: No response after first contact
A114: L10113 | B114: 2023-12-26 | C114: Instagram Ads | D114: Instagram | E114: DA_Dec23_Website_Lead_Generation | F114: Website Development | G114: Contacted | H114: No | I114: 41 | J114: 1456.89 | K114: No | L114: 0 | N114: No response after first contact
A115: L10114 | B115: 2023-12-26 | C115: Instagram Ads | D115: Instagram | E115: DA_Dec23_Website_Lead_Generation | F115: Website Development | G115: Lost | H115: No | I115: 41 | J115: 1235.89 | K115: No | L115: 0 | N115: Information request only
... A293: L10292 | B293: 2024-02-15 | C293: Facebook Ads | D293: Facebook | E293: DA_Feb24_Social_Media_Audit | F293: Social Media Marketing | G293: Lost | H293: No | I293: 15 | J293: 593.34 | K293: No | L293: 0 | N293: Outside target segment
A294: L10293 | B294: 2024-02-15 | C294: Facebook Ads | D294: Facebook | E294: DA_Feb24_Social_Media_Audit | F294: Social Media Marketing | G294: Won | H294: Yes | I294: 88 | J294: 1033.37 | K294: Yes | L294: 756.41 | M294: 2024-03-14 | N294: Converted after proposal follow-up
A295: L10294 | B295: 2024-02-15 | C295: Facebook Ads | D295: Facebook | E295: DA_Feb24_Social_Media_Audit | F295: Social Media Marketing | G295: Unqualified | H295: No | I295: 31 | J295: 0 | K295: No | L295: 0 | N295: Outside target segment
A296: L10295 | B296: 2024-02-16 | C296: Facebook Ads | D296: Facebook | E296: DA_Feb24_Social_Media_Audit | F296: Social Media Marketing | G296: Contacted | H296: No | I296: 42 | J296: 541.76 | K296: No | L296: 0 | N296: Outside target segment
A297: L10296 | B297: 2024-02-16 | C297: Facebook Ads | D297: Facebook | E297: DA_Feb24_Social_Media_Audit | F297: Social Media Marketing | G297: Lost | H297: No | I297: 39 | J297: 701.33 | K297: No | L297: 0 | N297: Information request only
A298: L10297 | B298: 2024-02-16 | C298: Facebook Ads | D298: Facebook | E298: DA_Feb24_Social_Media_Audit | F298: Social Media Marketing | G298: Lost | H298: No | I298: 36 | J298: 290.74 | K298: No | L298: 0 | N298: No response after first contact
A299: L10298 | B299: 2024-02-16 | C299: Facebook Ads | D299: Facebook | E299: DA_Feb24_Social_Media_Audit | F299: Social Media Marketing | G299: Contacted | H299: No | I299: 60 | J299: 529.16 | K299: No | L299: 0 | N299: Budget too low
A300: L10299 | B300: 2024-02-16 | C300: Facebook Ads | D300: Facebook | E300: DA_Feb24_Social_Media_Audit | F300: Social Media Marketing | G300: Unqualified | H300: No | I300: 20 | J300: 0 | K300: No | L300: 0 | N300: Information request only
A301: L10300 | B301: 2024-02-16 | C301: Facebook Ads | D301: Facebook | E301: DA_Feb24_Social_Media_Audit | F301: Social Media Marketing | G301: Lost | H301: No | I301: 51 | J301: 645.38 | K301: No | L301: 0 | N301: No response after first contact
A302: L10301 | B302: 2024-02-16 | C302: Facebook Ads | D302: Facebook | E302: DA_Feb24_Social_Media_Audit | F302: Social Media Marketing | G302: Contacted | H302: Yes | I302: 92 | J302: 1002.87 | K302: No | L302: 0 | N302: Needs follow-up
A303: L10302 | B303: 2024-02-16 | C303: Instagram Ads | D303: Instagram | E303: DA_Feb24_Social_Media_Audit | F303: Social Media Marketing | G303: Contacted | H303: No | I303: 25 | J303: 421.77 | K303: No | L303: 0 | N303: Budget too low
A304: L10303 | B304: 2024-02-17 | C304: Facebook Ads | D304: Facebook | E304: DA_Feb24_Social_Media_Audit | F304: Social Media Marketing | G304: Unqualified | H304: No | I304: 21 | J304: 0 | K304: No | L304: 0 | N304: Information request only
A305: L10304 | B305: 2024-02-17 | C305: Facebook Ads | D305: Facebook | E305: DA_Feb24_Social_Media_Audit | F305: Social Media Marketing | G305: Qualified | H305: Yes | I305: 62 | J305: 891.85 | K305: No | L305: 0 | N305: Qualified but not closed yet
A306: L10305 | B306: 2024-02-17 | C306: Facebook Ads | D306: Facebook | E306: DA_Feb24_Social_Media_Audit | F306: Social Media Marketing | G306: Contacted | H306: No | I306: 30 | J306: 247.76 | K306: No | L306: 0 | N306: Information request only
... A373: L10372 | B373: 2024-03-02 | C373: Instagram Ads | D373: Instagram | E373: DA_Mar24_Startup_Branding_Offer | F373: Branding & Design | G373: Contacted | H373: No | I373: 39 | J373: 917.68 | K373: No | L373: 0 | N373: No response after first contact
A374: L10373 | B374: 2024-03-03 | C374: Facebook Ads | D374: Facebook | E374: DA_Mar24_Startup_Branding_Offer | F374: Branding & Design | G374: Won | H374: Yes | I374: 90 | J374: 1507.51 | K374: Yes | L374: 1455.01 | M374: 2024-04-05 | N374: Converted after proposal follow-up
A375: L10374 | B375: 2024-03-03 | C375: Facebook Ads | D375: Facebook | E375: DA_Mar24_Startup_Branding_Offer | F375: Branding & Design | G375: Lost | H375: No | I375: 35 | J375: 899.8 | K375: No | L375: 0 | N375: Information request only
...

Sheet Cleaned_Daily
A1: Date | B1: Channel | C1: Platform | D1: Campaign Name | E1: Service | F1: Spend USD | G1: Impressions | H1: Clicks | I1: Sessions | J1: Leads | K1: Qualified Leads | L1: Customers | M1: Revenue USD | N1: CTR | O1: CPC | P1: Conversion Rate | Q1: Cost per Lead | R1: Cost per Qualified Lead | S1: ROAS | T1: ROI
A2: 2023-12-01 | B2: Direct | C2: direct / none | D2: (direct) | E2: SEO Services | F2: 0 | G2: 37 | H2: 37 | I2: 37 | J2: 0 | K2: 0 | L2: 0 | M2: 0 | N2: =IFERROR(H2/G2,0) | O2: =IFERROR(F2/H2,0) | P2: =IFERROR(J2/H2,0) | Q2: =IFERROR(F2/J2,0) | R2: =IFERROR(F2/K2,0) | S2: =IFERROR(M2/F2,0) | T2: =IFERROR((M2-F2)/F2,0)
A3: 2023-12-01 | B3: Facebook Ads | C3: Facebook | D3: DA_Dec23_Website_Lead_Generation | E3: Website Development | F3: 41.7 | G3: 9314 | H3: 150 | I3: 118 | J3: 5 | K3: 0 | L3: 0 | M3: 0 | N3: =IFERROR(H3/G3,0) | O3: =IFERROR(F3/H3,0) | P3: =IFERROR(J3/H3,0) | Q3: =IFERROR(F3/J3,0) | R3: =IFERROR(F3/K3,0) | S3: =IFERROR(M3/F3,0) | T3: =IFERROR((M3-F3)/F3,0)
A4: 2023-12-01 | B4: Google Ads | C4: Google Search | D4: Search_Dec23_Website_Lead_Generation | E4: Website Development | F4: 72.68 | G4: 1135 | H4: 65 | I4: 52 | J4: 5 | K4: 2 | L4: 0 | M4: 0 | N4: =IFERROR(H4/G4,0) | O4: =IFERROR(F4/H4,0) | P4: =IFERROR(J4/H4,0) | Q4: =IFERROR(F4/J4,0) | R4: =IFERROR(F4/K4,0) | S4: =IFERROR(M4/F4,0) | T4: =IFERROR((M4-F4)/F4,0)
A5: 2023-12-01 | B5: Instagram Ads | C5: Instagram | D5: DA_Dec23_Website_Lead_Generation | E5: Website Development | F5: 47.78 | G5: 7547 | H5: 96 | I5: 73 | J5: 2 | K5: 2 | L5: 0 | M5: 0 | N5: =IFERROR(H5/G5,0) | O5: =IFERROR(F5/H5,0) | P5: =IFERROR(J5/H5,0) | Q5: =IFERROR(F5/J5,0) | R5: =IFERROR(F5/K5,0) | S5: =IFERROR(M5/F5,0) | T5: =IFERROR((M5-F5)/F5,0)
A6: 2023-12-01 | B6: Referral | C6: facebook.com / referral | D6: (referral) | E6: Branding & Design | F6: 0 | G6: 18 | H6: 18 | I6: 18 | J6: 0 | K6: 0 | L6: 0 | M6: 0 | N6: =IFERROR(H6/G6,0) | O6: =IFERROR(F6/H6,0) | P6: =IFERROR(J6/H6,0) | Q6: =IFERROR(F6/J6,0) | R6: =IFERROR(F6/K6,0) | S6: =IFERROR(M6/F6,0) | T6: =IFERROR((M6-F6)/F6,0)
A7: 2023-12-01 | B7: Referral | C7: instagram.com / referral | D7: (referral) | E7: Social Media Marketing | F7: 0 | G7: 11 | H7: 11 | I7: 11 | J7: 0 | K7: 0 | L7: 0 | M7: 0 | N7: =IFERROR(H7/G7,0) | O7: =IFERROR(F7/H7,0) | P7: =IFERROR(J7/H7,0) | Q7: =IFERROR(F7/J7,0) | R7: =IFERROR(F7/K7,0) | S7: =IFERROR(M7/F7,0) | T7: =IFERROR((M7-F7)/F7,0)
A8: 2023-12-01 | B8: Referral | C8: linkedin.com / referral | D8: (referral) | E8: Branding & Design | F8: 0 | G8: 18 | H8: 18 | I8: 18 | J8: 0 | K8: 0 | L8: 0 | M8: 0 | N8: =IFERROR(H8/G8,0) | O8: =IFERROR(F8/H8,0) | P8: =IFERROR(J8/H8,0) | Q8: =IFERROR(F8/J8,0) | R8: =IFERROR(F8/K8,0) | S8: =IFERROR(M8/F8,0) | T8: =IFERROR((M8-F8)/F8,0)
A9: 2023-12-01 | B9: SEO | C9: google / organic | D9: (organic) | E9: Website Development | F9: 0 | G9: 88 | H9: 88 | I9: 88 | J9: 1 | K9: 0 | L9: 0 | M9: 0 | N9: =IFERROR(H9/G9,0) | O9: =IFERROR(F9/H9,0) | P9: =IFERROR(J9/H9,0) | Q9: =IFERROR(F9/J9,0) | R9: =IFERROR(F9/K9,0) | S9: =IFERROR(M9/F9,0) | T9: =IFERROR((M9-F9)/F9,0)
A10: 2023-12-02 | B10: Direct | C10: direct / none | D10: (direct) | E10: eCommerce Website | F10: 0 | G10: 27 | H10: 27 | I10: 27 | J10: 0 | K10: 0 | L10: 0 | M10: 0 | N10: =IFERROR(H10/G10,0) | O10: =IFERROR(F10/H10,0) | P10: =IFERROR(J10/H10,0) | Q10: =IFERROR(F10/J10,0) | R10: =IFERROR(F10/K10,0) | S10: =IFERROR(M10/F10,0) | T10: =IFERROR((M10-F10)/F10,0)
A11: 2023-12-02 | B11: Facebook Ads | C11: Facebook | D11: DA_Dec23_Website_Lead_Generation | E11: Website Development | F11: 37.91 | G11: 5697 | H11: 58 | I11: 46 | J11: 2 | K11: 0 | L11: 0 | M11: 0 | N11: =IFERROR(H11/G11,0) | O11: =IFERROR(F11/H11,0) | P11: =IFERROR(J11/H11,0) | Q11: =IFERROR(F11/J11,0) | R11: =IFERROR(F11/K11,0) | S11: =IFERROR(M11/F11,0) | T11: =IFERROR((M11-F11)/F11,0)
A12: 2023-12-02 | B12: Google Ads | C12: Google Search | D12: Search_Dec23_Website_Lead_Generation | E12: Website Development | F12: 88.75 | G12: 1550 | H12: 111 | I12: 89 | J12: 7 | K12: 3 | L12: 0 | M12: 0 | N12: =IFERROR(H12/G12,0) | O12: =IFERROR(F12/H12,0) | P12: =IFERROR(J12/H12,0) | Q12: =IFERROR(F12/J12,0) | R12: =IFERROR(F12/K12,0) | S12: =IFERROR(M12/F12,0) | T12: =IFERROR((M12-F12)/F12,0)
A13: 2023-12-02 | B13: Instagram Ads | C13: Instagram | D13: DA_Dec23_Website_Lead_Generation | E13: Website Development | F13: 31.45 | G13: 5040 | H13: 52 | I13: 40 | J13: 0 | K13: 0 | L13: 0 | M13: 0 | N13: =IFERROR(H13/G13,0) | O13: =IFERROR(F13/H13,0) | P13: =IFERROR(J13/H13,0) | Q13: =IFERROR(F13/J13,0) | R13: =IFERROR(F13/K13,0) | S13: =IFERROR(M13/F13,0) | T13: =IFERROR((M13-F13)/F13,0)
... A3047: 2024-12-31 | B3047: SEO | C3047: google / organic | D3047: (organic) | E3047: Website Development | F3047: 0 | G3047: 108 | H3047: 108 | I3047: 108 | J3047: 2 | K3047: 0 | L3047: 0 | M3047: 0 | N3047: =IFERROR(H3047/G3047,0) | O3047: =IFERROR(F3047/H3047,0) | P3047: =IFERROR(J3047/H3047,0) | Q3047: =IFERROR(F3047/J3047,0) | R3047: =IFERROR(F3047/K3047,0) | S3047: =IFERROR(M3047/F3047,0) | T3047: =IFERROR((M3047-F3047)/F3047,0)

Sheet Channel_KPIs
A1: Channel | B1: Spend USD | C1: Impressions | D1: Clicks | E1: Sessions | F1: Leads | G1: Qualified Leads | H1: Customers | I1: Revenue USD | J1: CTR | K1: CPC | L1: Conversion Rate | M1: Cost per Lead | N1: Cost per Qualified Lead | O1: ROAS | P1: ROI | Q1: Lead Qualification Rate | R1: Qualified-to-Customer Rate
A2: Google Ads | B2: =SUMIFS(Cleaned_Daily!$F$2:$F$3047,Cleaned_Daily!$B$2:$B$3047,$A2) | C2: =SUMIFS(Cleaned_Daily!$G$2:$G$3047,Cleaned_Daily!$B$2:$B$3047,$A2) | D2: =SUMIFS(Cleaned_Daily!$H$2:$H$3047,Cleaned_Daily!$B$2:$B$3047,$A2) | E2: =SUMIFS(Cleaned_Daily!$I$2:$I$3047,Cleaned_Daily!$B$2:$B$3047,$A2) | F2: =SUMIFS(Cleaned_Daily!$J$2:$J$3047,Cleaned_Daily!$B$2:$B$3047,$A2) | G2: =SUMIFS(Cleaned_Daily!$K$2:$K$3047,Cleaned_Daily!$B$2:$B$3047,$A2) | H2: =SUMIFS(Cleaned_Daily!$L$2:$L$3047,Cleaned_Daily!$B$2:$B$3047,$A2) | I2: =SUMIFS(Cleaned_Daily!$M$2:$M$3047,Cleaned_Daily!$B$2:$B$3047,$A2) | J2: =IFERROR(D2/C2,0) | K2: =IFERROR(B2/D2,0) | L2: =IFERROR(F2/D2,0) | M2: =IFERROR(B2/F2,0) | N2: =IFERROR(B2/G2,0) | O2: =IFERROR(I2/B2,0) | P2: =IFERROR((I2-B2)/B2,0) | Q2: =IFERROR(G2/F2,0) | R2: =IFERROR(H2/G2,0)
A3: SEO | B3: =SUMIFS(Cleaned_Daily!$F$2:$F$3047,Cleaned_Daily!$B$2:$B$3047,$A3) | C3: =SUMIFS(Cleaned_Daily!$G$2:$G$3047,Cleaned_Daily!$B$2:$B$3047,$A3) | D3: =SUMIFS(Cleaned_Daily!$H$2:$H$3047,Cleaned_Daily!$B$2:$B$3047,$A3) | E3: =SUMIFS(Cleaned_Daily!$I$2:$I$3047,Cleaned_Daily!$B$2:$B$3047,$A3) | F3: =SUMIFS(Cleaned_Daily!$J$2:$J$3047,Cleaned_Daily!$B$2:$B$3047,$A3) | G3: =SUMIFS(Cleaned_Daily!$K$2:$K$3047,Cleaned_Daily!$B$2:$B$3047,$A3) | H3: =SUMIFS(Cleaned_Daily!$L$2:$L$3047,Cleaned_Daily!$B$2:$B$3047,$A3) | I3: =SUMIFS(Cleaned_Daily!$M$2:$M$3047,Cleaned_Daily!$B$2:$B$3047,$A3) | J3: =IFERROR(D3/C3,0) | K3: =IFERROR(B3/D3,0) | L3: =IFERROR(F3/D3,0) | M3: =IFERROR(B3/F3,0) | N3: =IFERROR(B3/G3,0) | O3: =IFERROR(I3/B3,0) | P3: =IFERROR((I3-B3)/B3,0) | Q3: =IFERROR(G3/F3,0) | R3: =IFERROR(H3/G3,0)
A4: Facebook Ads | B4: =SUMIFS(Cleaned_Daily!$F$2:$F$3047,Cleaned_Daily!$B$2:$B$3047,$A4) | C4: =SUMIFS(Cleaned_Daily!$G$2:$G$3047,Cleaned_Daily!$B$2:$B$3047,$A4) | D4: =SUMIFS(Cleaned_Daily!$H$2:$H$3047,Cleaned_Daily!$B$2:$B$3047,$A4) | E4: =SUMIFS(Cleaned_Daily!$I$2:$I$3047,Cleaned_Daily!$B$2:$B$3047,$A4) | F4: =SUMIFS(Cleaned_Daily!$J$2:$J$3047,Cleaned_Daily!$B$2:$B$3047,$A4) | G4: =SUMIFS(Cleaned_Daily!$K$2:$K$3047,Cleaned_Daily!$B$2:$B$3047,$A4) | H4: =SUMIFS(Cleaned_Daily!$L$2:$L$3047,Cleaned_Daily!$B$2:$B$3047,$A4) | I4: =SUMIFS(Cleaned_Daily!$M$2:$M$3047,Cleaned_Daily!$B$2:$B$3047,$A4) | J4: =IFERROR(D4/C4,0) | K4: =IFERROR(B4/D4,0) | L4: =IFERROR(F4/D4,0) | M4: =IFERROR(B4/F4,0) | N4: =IFERROR(B4/G4,0) | O4: =IFERROR(I4/B4,0) | P4: =IFERROR((I4-B4)/B4,0) | Q4: =IFERROR(G4/F4,0) | R4: =IFERROR(H4/G4,0)
A5: Direct | B5: =SUMIFS(Cleaned_Daily!$F$2:$F$3047,Cleaned_Daily!$B$2:$B$3047,$A5) | C5: =SUMIFS(Cleaned_Daily!$G$2:$G$3047,Cleaned_Daily!$B$2:$B$3047,$A5) | D5: =SUMIFS(Cleaned_Daily!$H$2:$H$3047,Cleaned_Daily!$B$2:$B$3047,$A5) | E5: =SUMIFS(Cleaned_Daily!$I$2:$I$3047,Cleaned_Daily!$B$2:$B$3047,$A5) | F5: =SUMIFS(Cleaned_Daily!$J$2:$J$3047,Cleaned_Daily!$B$2:$B$3047,$A5) | G5: =SUMIFS(Cleaned_Daily!$K$2:$K$3047,Cleaned_Daily!$B$2:$B$3047,$A5) | H5: =SUMIFS(Cleaned_Daily!$L$2:$L$3047,Cleaned_Daily!$B$2:$B$3047,$A5) | I5: =SUMIFS(Cleaned_Daily!$M$2:$M$3047,Cleaned_Daily!$B$2:$B$3047,$A5) | J5: =IFERROR(D5/C5,0) | K5: =IFERROR(B5/D5,0) | L5: =IFERROR(F5/D5,0) | M5: =IFERROR(B5/F5,0) | N5: =IFERROR(B5/G5,0) | O5: =IFERROR(I5/B5,0) | P5: =IFERROR((I5-B5)/B5,0) | Q5: =IFERROR(G5/F5,0) | R5: =IFERROR(H5/G5,0)
A6: Instagram Ads | B6: =SUMIFS(Cleaned_Daily!$F$2:$F$3047,Cleaned_Daily!$B$2:$B$3047,$A6) | C6: =SUMIFS(Cleaned_Daily!$G$2:$G$3047,Cleaned_Daily!$B$2:$B$3047,$A6) | D6: =SUMIFS(Cleaned_Daily!$H$2:$H$3047,Cleaned_Daily!$B$2:$B$3047,$A6) | E6: =SUMIFS(Cleaned_Daily!$I$2:$I$3047,Cleaned_Daily!$B$2:$B$3047,$A6) | F6: =SUMIFS(Cleaned_Daily!$J$2:$J$3047,Cleaned_Daily!$B$2:$B$3047,$A6) | G6: =SUMIFS(Cleaned_Daily!$K$2:$K$3047,Cleaned_Daily!$B$2:$B$3047,$A6) | H6: =SUMIFS(Cleaned_Daily!$L$2:$L$3047,Cleaned_Daily!$B$2:$B$3047,$A6) | I6: =SUMIFS(Cleaned_Daily!$M$2:$M$3047,Cleaned_Daily!$B$2:$B$3047,$A6) | J6: =IFERROR(D6/C6,0) | K6: =IFERROR(B6/D6,0) | L6: =IFERROR(F6/D6,0) | M6: =IFERROR(B6/F6,0) | N6: =IFERROR(B6/G6,0) | O6: =IFERROR(I6/B6,0) | P6: =IFERROR((I6-B6)/B6,0) | Q6: =IFERROR(G6/F6,0) | R6: =IFERROR(H6/G6,0)
A7: Email | B7: =SUMIFS(Cleaned_Daily!$F$2:$F$3047,Cleaned_Daily!$B$2:$B$3047,$A7) | C7: =SUMIFS(Cleaned_Daily!$G$2:$G$3047,Cleaned_Daily!$B$2:$B$3047,$A7) | D7: =SUMIFS(Cleaned_Daily!$H$2:$H$3047,Cleaned_Daily!$B$2:$B$3047,$A7) | E7: =SUMIFS(Cleaned_Daily!$I$2:$I$3047,Cleaned_Daily!$B$2:$B$3047,$A7) | F7: =SUMIFS(Cleaned_Daily!$J$2:$J$3047,Cleaned_Daily!$B$2:$B$3047,$A7) | G7: =SUMIFS(Cleaned_Daily!$K$2:$K$3047,Cleaned_Daily!$B$2:$B$3047,$A7) | H7: =SUMIFS(Cleaned_Daily!$L$2:$L$3047,Cleaned_Daily!$B$2:$B$3047,$A7) | I7: =SUMIFS(Cleaned_Daily!$M$2:$M$3047,Cleaned_Daily!$B$2:$B$3047,$A7) | J7: =IFERROR(D7/C7,0) | K7: =IFERROR(B7/D7,0) | L7: =IFERROR(F7/D7,0) | M7: =IFERROR(B7/F7,0) | N7: =IFERROR(B7/G7,0) | O7: =IFERROR(I7/B7,0) | P7: =IFERROR((I7-B7)/B7,0) | Q7: =IFERROR(G7/F7,0) | R7: =IFERROR(H7/G7,0)
A8: Referral | B8: =SUMIFS(Cleaned_Daily!$F$2:$F$3047,Cleaned_Daily!$B$2:$B$3047,$A8) | C8: =SUMIFS(Cleaned_Daily!$G$2:$G$3047,Cleaned_Daily!$B$2:$B$3047,$A8) | D8: =SUMIFS(Cleaned_Daily!$H$2:$H$3047,Cleaned_Daily!$B$2:$B$3047,$A8) | E8: =SUMIFS(Cleaned_Daily!$I$2:$I$3047,Cleaned_Daily!$B$2:$B$3047,$A8) | F8: =SUMIFS(Cleaned_Daily!$J$2:$J$3047,Cleaned_Daily!$B$2:$B$3047,$A8) | G8: =SUMIFS(Cleaned_Daily!$K$2:$K$3047,Cleaned_Daily!$B$2:$B$3047,$A8) | H8: =SUMIFS(Cleaned_Daily!$L$2:$L$3047,Cleaned_Daily!$B$2:$B$3047,$A8) | I8: =SUMIFS(Cleaned_Daily!$M$2:$M$3047,Cleaned_Daily!$B$2:$B$3047,$A8) | J8: =IFERROR(D8/C8,0) | K8: =IFERROR(B8/D8,0) | L8: =IFERROR(F8/D8,0) | M8: =IFERROR(B8/F8,0) | N8: =IFERROR(B8/G8,0) | O8: =IFERROR(I8/B8,0) | P8: =IFERROR((I8-B8)/B8,0) | Q8: =IFERROR(G8/F8,0) | R8: =IFERROR(H8/G8,0)

Sheet Campaign_KPIs
A1: Campaign Name | B1: Spend USD | C1: Impressions | D1: Clicks | E1: Sessions | F1: Leads | G1: Qualified Leads | H1: Customers | I1: Revenue USD | J1: CTR | K1: CPC | L1: Conversion Rate | M1: Cost per Lead | N1: Cost per Qualified Lead | O1: ROAS | P1: ROI | Q1: Lead Qualification Rate | R1: Qualified-to-Customer Rate
A2: (organic) | B2: =SUMIFS(Cleaned_Daily!$F$2:$F$3047,Cleaned_Daily!$D$2:$D$3047,$A2) | C2: =SUMIFS(Cleaned_Daily!$G$2:$G$3047,Cleaned_Daily!$D$2:$D$3047,$A2) | D2: =SUMIFS(Cleaned_Daily!$H$2:$H$3047,Cleaned_Daily!$D$2:$D$3047,$A2) | E2: =SUMIFS(Cleaned_Daily!$I$2:$I$3047,Cleaned_Daily!$D$2:$D$3047,$A2) | F2: =SUMIFS(Cleaned_Daily!$J$2:$J$3047,Cleaned_Daily!$D$2:$D$3047,$A2) | G2: =SUMIFS(Cleaned_Daily!$K$2:$K$3047,Cleaned_Daily!$D$2:$D$3047,$A2) | H2: =SUMIFS(Cleaned_Daily!$L$2:$L$3047,Cleaned_Daily!$D$2:$D$3047,$A2) | I2: =SUMIFS(Cleaned_Daily!$M$2:$M$3047,Cleaned_Daily!$D$2:$D$3047,$A2) | J2: =IFERROR(D2/C2,0) | K2: =IFERROR(B2/D2,0) | L2: =IFERROR(F2/D2,0) | M2: =IFERROR(B2/F2,0) | N2: =IFERROR(B2/G2,0) | O2: =IFERROR(I2/B2,0) | P2: =IFERROR((I2-B2)/B2,0) | Q2: =IFERROR(G2/F2,0) | R2: =IFERROR(H2/G2,0)
A3: Search_Sep24_School_System_Demo | B3: =SUMIFS(Cleaned_Daily!$F$2:$F$3047,Cleaned_Daily!$D$2:$D$3047,$A3) | C3: =SUMIFS(Cleaned_Daily!$G$2:$G$3047,Cleaned_Daily!$D$2:$D$3047,$A3) | D3: =SUMIFS(Cleaned_Daily!$H$2:$H$3047,Cleaned_Daily!$D$2:$D$3047,$A3) | E3: =SUMIFS(Cleaned_Daily!$I$2:$I$3047,Cleaned_Daily!$D$2:$D$3047,$A3) | F3: =SUMIFS(Cleaned_Daily!$J$2:$J$3047,Cleaned_Daily!$D$2:$D$3047,$A3) | G3: =SUMIFS(Cleaned_Daily!$K$2:$K$3047,Cleaned_Daily!$D$2:$D$3047,$A3) | H3: =SUMIFS(Cleaned_Daily!$L$2:$L$3047,Cleaned_Daily!$D$2:$D$3047,$A3) | I3: =SUMIFS(Cleaned_Daily!$M$2:$M$3047,Cleaned_Daily!$D$2:$D$3047,$A3) | J3: =IFERROR(D3/C3,0) | K3: =IFERROR(B3/D3,0) | L3: =IFERROR(F3/D3,0) | M3: =IFERROR(B3/F3,0) | N3: =IFERROR(B3/G3,0) | O3: =IFERROR(I3/B3,0) | P3: =IFERROR((I3-B3)/B3,0) | Q3: =IFERROR(G3/F3,0) | R3: =IFERROR(H3/G3,0)
A4: Search_Jan24_eCommerce_Growth_Push | B4: =SUMIFS(Cleaned_Daily!$F$2:$F$3047,Cleaned_Daily!$D$2:$D$3047,$A4) | C4: =SUMIFS(Cleaned_Daily!$G$2:$G$3047,Cleaned_Daily!$D$2:$D$3047,$A4) | D4: =SUMIFS(Cleaned_Daily!$H$2:$H$3047,Cleaned_Daily!$D$2:$D$3047,$A4) | E4: =SUMIFS(Cleaned_Daily!$I$2:$I$3047,Cleaned_Daily!$D$2:$D$3047,$A4) | F4: =SUMIFS(Cleaned_Daily!$J$2:$J$3047,Cleaned_Daily!$D$2:$D$3047,$A4) | G4: =SUMIFS(Cleaned_Daily!$K$2:$K$3047,Cleaned_Daily!$D$2:$D$3047,$A4) | H4: =SUMIFS(Cleaned_Daily!$L$2:$L$3047,Cleaned_Daily!$D$2:$D$3047,$A4) | I4: =SUMIFS(Cleaned_Daily!$M$2:$M$3047,Cleaned_Daily!$D$2:$D$3047,$A4) | J4: =IFERROR(D4/C4,0) | K4: =IFERROR(B4/D4,0) | L4: =IFERROR(F4/D4,0) | M4: =IFERROR(B4/F4,0) | N4: =IFERROR(B4/G4,0) | O4: =IFERROR(I4/B4,0) | P4: =IFERROR((I4-B4)/B4,0) | Q4: =IFERROR(G4/F4,0) | R4: =IFERROR(H4/G4,0)
A5: Search_Jun24_Business_Automation_Demo | B5: =SUMIFS(Cleaned_Daily!$F$2:$F$3047,Cleaned_Daily!$D$2:$D$3047,$A5) | C5: =SUMIFS(Cleaned_Daily!$G$2:$G$3047,Cleaned_Daily!$D$2:$D$3047,$A5) | D5: =SUMIFS(Cleaned_Daily!$H$2:$H$3047,Cleaned_Daily!$D$2:$D$3047,$A5) | E5: =SUMIFS(Cleaned_Daily!$I$2:$I$3047,Cleaned_Daily!$D$2:$D$3047,$A5) | F5: =SUMIFS(Cleaned_Daily!$J$2:$J$3047,Cleaned_Daily!$D$2:$D$3047,$A5) | G5: =SUMIFS(Cleaned_Daily!$K$2:$K$3047,Cleaned_Daily!$D$2:$D$3047,$A5) | H5: =SUMIFS(Cleaned_Daily!$L$2:$L$3047,Cleaned_Daily!$D$2:$D$3047,$A5) | I5: =SUMIFS(Cleaned_Daily!$M$2:$M$3047,Cleaned_Daily!$D$2:$D$3047,$A5) | J5: =IFERROR(D5/C5,0) | K5: =IFERROR(B5/D5,0) | L5: =IFERROR(F5/D5,0) | M5: =IFERROR(B5/F5,0) | N5: =IFERROR(B5/G5,0) | O5: =IFERROR(I5/B5,0) | P5: =IFERROR((I5-B5)/B5,0) | Q5: =IFERROR(G5/F5,0) | R5: =IFERROR(H5/G5,0)
A6: Search_Jul24_eCommerce_Monsoon_Offer | B6: =SUMIFS(Cleaned_Daily!$F$2:$F$3047,Cleaned_Daily!$D$2:$D$3047,$A6) | C6: =SUMIFS(Cleaned_Daily!$G$2:$G$3047,Cleaned_Daily!$D$2:$D$3047,$A6) | D6: =SUMIFS(Cleaned_Daily!$H$2:$H$3047,Cleaned_Daily!$D$2:$D$3047,$A6) | E6: =SUMIFS(Cleaned_Daily!$I$2:$I$3047,Cleaned_Daily!$D$2:$D$3047,$A6) | F6: =SUMIFS(Cleaned_Daily!$J$2:$J$3047,Cleaned_Daily!$D$2:$D$3047,$A6) | G6: =SUMIFS(Cleaned_Daily!$K$2:$K$3047,Cleaned_Daily!$D$2:$D$3047,$A6) | H6: =SUMIFS(Cleaned_Daily!$L$2:$L$3047,Cleaned_Daily!$D$2:$D$3047,$A6) | I6: =SUMIFS(Cleaned_Daily!$M$2:$M$3047,Cleaned_Daily!$D$2:$D$3047,$A6) | J6: =IFERROR(D6/C6,0) | K6: =IFERROR(B6/D6,0) | L6: =IFERROR(F6/D6,0) | M6: =IFERROR(B6/F6,0) | N6: =IFERROR(B6/G6,0) | O6: =IFERROR(I6/B6,0) | P6: =IFERROR((I6-B6)/B6,0) | Q6: =IFERROR(G6/F6,0) | R6: =IFERROR(H6/G6,0)
A7: Search_Dec23_Website_Lead_Generation | B7: =SUMIFS(Cleaned_Daily!$F$2:$F$3047,Cleaned_Daily!$D$2:$D$3047,$A7) | C7: =SUMIFS(Cleaned_Daily!$G$2:$G$3047,Cleaned_Daily!$D$2:$D$3047,$A7) | D7: =SUMIFS(Cleaned_Daily!$H$2:$H$3047,Cleaned_Daily!$D$2:$D$3047,$A7) | E7: =SUMIFS(Cleaned_Daily!$I$2:$I$3047,Cleaned_Daily!$D$2:$D$3047,$A7) | F7: =SUMIFS(Cleaned_Daily!$J$2:$J$3047,Cleaned_Daily!$D$2:$D$3047,$A7) | G7: =SUMIFS(Cleaned_Daily!$K$2:$K$3047,Cleaned_Daily!$D$2:$D$3047,$A7) | H7: =SUMIFS(Cleaned_Daily!$L$2:$L$3047,Cleaned_Daily!$D$2:$D$3047,$A7) | I7: =SUMIFS(Cleaned_Daily!$M$2:$M$3047,Cleaned_Daily!$D$2:$D$3047,$A7) | J7: =IFERROR(D7/C7,0) | K7: =IFERROR(B7/D7,0) | L7: =IFERROR(F7/D7,0) | M7: =IFERROR(B7/F7,0) | N7: =IFERROR(B7/G7,0) | O7: =IFERROR(I7/B7,0) | P7: =IFERROR((I7-B7)/B7,0) | Q7: =IFERROR(G7/F7,0) | R7: =IFERROR(H7/G7,0)
A8: Search_Aug24_News_Portal_Leads | B8: =SUMIFS(Cleaned_Daily!$F$2:$F$3047,Cleaned_Daily!$D$2:$D$3047,$A8) | C8: =SUMIFS(Cleaned_Daily!$G$2:$G$3047,Cleaned_Daily!$D$2:$D$3047,$A8) | D8: =SUMIFS(Cleaned_Daily!$H$2:$H$3047,Cleaned_Daily!$D$2:$D$3047,$A8) | E8: =SUMIFS(Cleaned_Daily!$I$2:$I$3047,Cleaned_Daily!$D$2:$D$3047,$A8) | F8: =SUMIFS(Cleaned_Daily!$J$2:$J$3047,Cleaned_Daily!$D$2:$D$3047,$A8) | G8: =SUMIFS(Cleaned_Daily!$K$2:$K$3047,Cleaned_Daily!$D$2:$D$3047,$A8) | H8: =SUMIFS(Cleaned_Daily!$L$2:$L$3047,Cleaned_Daily!$D$2:$D$3047,$A8) | I8: =SUMIFS(Cleaned_Daily!$M$2:$M$3047,Cleaned_Daily!$D$2:$D$3047,$A8) | J8: =IFERROR(D8/C8,0) | K8: =IFERROR(B8/D8,0) | L8: =IFERROR(F8/D8,0) | M8: =IFERROR(B8/F8,0) | N8: =IFERROR(B8/G8,0) | O8: =IFERROR(I8/B8,0) | P8: =IFERROR((I8-B8)/B8,0) | Q8: =IFERROR(G8/F8,0) | R8: =IFERROR(H8/G8,0)
A9: Search_Apr24_Website_Redesign_Leads | B9: =SUMIFS(Cleaned_Daily!$F$2:$F$3047,Cleaned_Daily!$D$2:$D$3047,$A9) | C9: =SUMIFS(Cleaned_Daily!$G$2:$G$3047,Cleaned_Daily!$D$2:$D$3047,$A9) | D9: =SUMIFS(Cleaned_Daily!$H$2:$H$3047,Cleaned_Daily!$D$2:$D$3047,$A9) | E9: =SUMIFS(Cleaned_Daily!$I$2:$I$3047,Cleaned_Daily!$D$2:$D$3047,$A9) | F9: =SUMIFS(Cleaned_Daily!$J$2:$J$3047,Cleaned_Daily!$D$2:$D$3047,$A9) | G9: =SUMIFS(Cleaned_Daily!$K$2:$K$3047,Cleaned_Daily!$D$2:$D$3047,$A9) | H9: =SUMIFS(Cleaned_Daily!$L$2:$L$3047,Cleaned_Daily!$D$2:$D$3047,$A9) | I9: =SUMIFS(Cleaned_Daily!$M$2:$M$3047,Cleaned_Daily!$D$2:$D$3047,$A9) | J9: =IFERROR(D9/C9,0) | K9: =IFERROR(B9/D9,0) | L9: =IFERROR(F9/D9,0) | M9: =IFERROR(B9/F9,0) | N9: =IFERROR(B9/G9,0) | O9: =IFERROR(I9/B9,0) | P9: =IFERROR((I9-B9)/B9,0) | Q9: =IFERROR(G9/F9,0) | R9: =IFERROR(H9/G9,0)
A10: Search_Nov24_Holiday_Website_Offer | B10: =SUMIFS(Cleaned_Daily!$F$2:$F$3047,Cleaned_Daily!$D$2:$D$3047,$A10) | C10: =SUMIFS(Cleaned_Daily!$G$2:$G$3047,Cleaned_Daily!$D$2:$D$3047,$A10) | D10: =SUMIFS(Cleaned_Daily!$H$2:$H$3047,Cleaned_Daily!$D$2:$D$3047,$A10) | E10: =SUMIFS(Cleaned_Daily!$I$2:$I$3047,Cleaned_Daily!$D$2:$D$3047,$A10) | F10: =SUMIFS(Cleaned_Daily!$J$2:$J$3047,Cleaned_Daily!$D$2:$D$3047,$A10) | G10: =SUMIFS(Cleaned_Daily!$K$2:$K$3047,Cleaned_Daily!$D$2:$D$3047,$A10) | H10: =SUMIFS(Cleaned_Daily!$L$2:$L$3047,Cleaned_Daily!$D$2:$D$3047,$A10) | I10: =SUMIFS(Cleaned_Daily!$M$2:$M$3047,Cleaned_Daily!$D$2:$D$3047,$A10) | J10: =IFERROR(D10/C10,0) | K10: =IFERROR(B10/D10,0) | L10: =IFERROR(F10/D10,0) | M10: =IFERROR(B10/F10,0) | N10: =IFERROR(B10/G10,0) | O10: =IFERROR(I10/B10,0) | P10: =IFERROR((I10-B10)/B10,0) | Q10: =IFERROR(G10/F10,0) | R10: =IFERROR(H10/G10,0)
A11: Search_Oct24_SEO_Ranking_Push | B11: =SUMIFS(Cleaned_Daily!$F$2:$F$3047,Cleaned_Daily!$D$2:$D$3047,$A11) | C11: =SUMIFS(Cleaned_Daily!$G$2:$G$3047,Cleaned_Daily!$D$2:$D$3047,$A11) | D11: =SUMIFS(Cleaned_Daily!$H$2:$H$3047,Cleaned_Daily!$D$2:$D$3047,$A11) | E11: =SUMIFS(Cleaned_Daily!$I$2:$I$3047,Cleaned_Daily!$D$2:$D$3047,$A11) | F11: =SUMIFS(Cleaned_Daily!$J$2:$J$3047,Cleaned_Daily!$D$2:$D$3047,$A11) | G11: =SUMIFS(Cleaned_Daily!$K$2:$K$3047,Cleaned_Daily!$D$2:$D$3047,$A11) | H11: =SUMIFS(Cleaned_Daily!$L$2:$L$3047,Cleaned_Daily!$D$2:$D$3047,$A11) | I11: =SUMIFS(Cleaned_Daily!$M$2:$M$3047,Cleaned_Daily!$D$2:$D$3047,$A11) | J11: =IFERROR(D11/C11,0) | K11: =IFERROR(B11/D11,0) | L11: =IFERROR(F11/D11,0) | M11: =IFERROR(B11/F11,0) | N11: =IFERROR(B11/G11,0) | O11: =IFERROR(I11/B11,0) | P11: =IFERROR((I11-B11)/B11,0) | Q11: =IFERROR(G11/F11,0) | R11: =IFERROR(H11/G11,0)
A12: Search_May24_SEO_Audit_Campaign | B12: =SUMIFS(Cleaned_Daily!$F$2:$F$3047,Cleaned_Daily!$D$2:$D$3047,$A12) | C12: =SUMIFS(Cleaned_Daily!$G$2:$G$3047,Cleaned_Daily!$D$2:$D$3047,$A12) | D12: =SUMIFS(Cleaned_Daily!$H$2:$H$3047,Cleaned_Daily!$D$2:$D$3047,$A12) | E12: =SUMIFS(Cleaned_Daily!$I$2:$I$3047,Cleaned_Daily!$D$2:$D$3047,$A12) | F12: =SUMIFS(Cleaned_Daily!$J$2:$J$3047,Cleaned_Daily!$D$2:$D$3047,$A12) | G12: =SUMIFS(Cleaned_Daily!$K$2:$K$3047,Cleaned_Daily!$D$2:$D$3047,$A12) | H12: =SUMIFS(Cleaned_Daily!$L$2:$L$3047,Cleaned_Daily!$D$2:$D$3047,$A12) | I12: =SUMIFS(Cleaned_Daily!$M$2:$M$3047,Cleaned_Daily!$D$2:$D$3047,$A12) | J12: =IFERROR(D12/C12,0) | K12: =IFERROR(B12/D12,0) | L12: =IFERROR(F12/D12,0) | M12: =IFERROR(B12/F12,0) | N12: =IFERROR(B12/G12,0) | O12: =IFERROR(I12/B12,0) | P12: =IFERROR((I12-B12)/B12,0) | Q12: =IFERROR(G12/F12,0) | R12: =IFERROR(H12/G12,0)
A13: Search_Feb24_Social_Media_Audit | B13: =SUMIFS(Cleaned_Daily!$F$2:$F$3047,Cleaned_Daily!$D$2:$D$3047,$A13) | C13: =SUMIFS(Cleaned_Daily!$G$2:$G$3047,Cleaned_Daily!$D$2:$D$3047,$A13) | D13: =SUMIFS(Cleaned_Daily!$H$2:$H$3047,Cleaned_Daily!$D$2:$D$3047,$A13) | E13: =SUMIFS(Cleaned_Daily!$I$2:$I$3047,Cleaned_Daily!$D$2:$D$3047,$A13) | F13: =SUMIFS(Cleaned_Daily!$J$2:$J$3047,Cleaned_Daily!$D$2:$D$3047,$A13) | G13: =SUMIFS(Cleaned_Daily!$K$2:$K$3047,Cleaned_Daily!$D$2:$D$3047,$A13) | H13: =SUMIFS(Cleaned_Daily!$L$2:$L$3047,Cleaned_Daily!$D$2:$D$3047,$A13) | I13: =SUMIFS(Cleaned_Daily!$M$2:$M$3047,Cleaned_Daily!$D$2:$D$3047,$A13) | J13: =IFERROR(D13/C13,0) | K13: =IFERROR(B13/D13,0) | L13: =IFERROR(F13/D13,0) | M13: =IFERROR(B13/F13,0) | N13: =IFERROR(B13/G13,0) | O13: =IFERROR(I13/B13,0) | P13: =IFERROR((I13-B13)/B13,0) | Q13: =IFERROR(G13/F13,0) | R13: =IFERROR(H13/G13,0)
... A56: Email_Dec24_New_Year_Growth_Plan_offer_reminder | B56: =SUMIFS(Cleaned_Daily!$F$2:$F$3047,Cleaned_Daily!$D$2:$D$3047,$A56) | C56: =SUMIFS(Cleaned_Daily!$G$2:$G$3047,Cleaned_Daily!$D$2:$D$3047,$A56) | D56: =SUMIFS(Cleaned_Daily!$H$2:$H$3047,Cleaned_Daily!$D$2:$D$3047,$A56) | E56: =SUMIFS(Cleaned_Daily!$I$2:$I$3047,Cleaned_Daily!$D$2:$D$3047,$A56) | F56: =SUMIFS(Cleaned_Daily!$J$2:$J$3047,Cleaned_Daily!$D$2:$D$3047,$A56) | G56: =SUMIFS(Cleaned_Daily!$K$2:$K$3047,Cleaned_Daily!$D$2:$D$3047,$A56) | H56: =SUMIFS(Cleaned_Daily!$L$2:$L$3047,Cleaned_Daily!$D$2:$D$3047,$A56) | I56: =SUMIFS(Cleaned_Daily!$M$2:$M$3047,Cleaned_Daily!$D$2:$D$3047,$A56) | J56: =IFERROR(D56/C56,0) | K56: =IFERROR(B56/D56,0) | L56: =IFERROR(F56/D56,0) | M56: =IFERROR(B56/F56,0) | N56: =IFERROR(B56/G56,0) | O56: =IFERROR(I56/B56,0) | P56: =IFERROR((I56-B56)/B56,0) | Q56: =IFERROR(G56/F56,0) | R56: =IFERROR(H56/G56,0)

Sheet Service_KPIs
A1: Service | B1: Spend USD | C1: Impressions | D1: Clicks | E1: Sessions | F1: Leads | G1: Qualified Leads | H1: Customers | I1: Revenue USD | J1: CTR | K1: CPC | L1: Conversion Rate | M1: Cost per Lead | N1: Cost per Qualified Lead | O1: ROAS | P1: ROI | Q1: Lead Qualification Rate | R1: Qualified-to-Customer Rate
A2: Website Development | B2: =SUMIFS(Cleaned_Daily!$F$2:$F$3047,Cleaned_Daily!$E$2:$E$3047,$A2) | C2: =SUMIFS(Cleaned_Daily!$G$2:$G$3047,Cleaned_Daily!$E$2:$E$3047,$A2) | D2: =SUMIFS(Cleaned_Daily!$H$2:$H$3047,Cleaned_Daily!$E$2:$E$3047,$A2) | E2: =SUMIFS(Cleaned_Daily!$I$2:$I$3047,Cleaned_Daily!$E$2:$E$3047,$A2) | F2: =SUMIFS(Cleaned_Daily!$J$2:$J$3047,Cleaned_Daily!$E$2:$E$3047,$A2) | G2: =SUMIFS(Cleaned_Daily!$K$2:$K$3047,Cleaned_Daily!$E$2:$E$3047,$A2) | H2: =SUMIFS(Cleaned_Daily!$L$2:$L$3047,Cleaned_Daily!$E$2:$E$3047,$A2) | I2: =SUMIFS(Cleaned_Daily!$M$2:$M$3047,Cleaned_Daily!$E$2:$E$3047,$A2) | J2: =IFERROR(D2/C2,0) | K2: =IFERROR(B2/D2,0) | L2: =IFERROR(F2/D2,0) | M2: =IFERROR(B2/F2,0) | N2: =IFERROR(B2/G2,0) | O2: =IFERROR(I2/B2,0) | P2: =IFERROR((I2-B2)/B2,0) | Q2: =IFERROR(G2/F2,0) | R2: =IFERROR(H2/G2,0)
A3: eCommerce Website | B3: =SUMIFS(Cleaned_Daily!$F$2:$F$3047,Cleaned_Daily!$E$2:$E$3047,$A3) | C3: =SUMIFS(Cleaned_Daily!$G$2:$G$3047,Cleaned_Daily!$E$2:$E$3047,$A3) | D3: =SUMIFS(Cleaned_Daily!$H$2:$H$3047,Cleaned_Daily!$E$2:$E$3047,$A3) | E3: =SUMIFS(Cleaned_Daily!$I$2:$I$3047,Cleaned_Daily!$E$2:$E$3047,$A3) | F3: =SUMIFS(Cleaned_Daily!$J$2:$J$3047,Cleaned_Daily!$E$2:$E$3047,$A3) | G3: =SUMIFS(Cleaned_Daily!$K$2:$K$3047,Cleaned_Daily!$E$2:$E$3047,$A3) | H3: =SUMIFS(Cleaned_Daily!$L$2:$L$3047,Cleaned_Daily!$E$2:$E$3047,$A3) | I3: =SUMIFS(Cleaned_Daily!$M$2:$M$3047,Cleaned_Daily!$E$2:$E$3047,$A3) | J3: =IFERROR(D3/C3,0) | K3: =IFERROR(B3/D3,0) | L3: =IFERROR(F3/D3,0) | M3: =IFERROR(B3/F3,0) | N3: =IFERROR(B3/G3,0) | O3: =IFERROR(I3/B3,0) | P3: =IFERROR((I3-B3)/B3,0) | Q3: =IFERROR(G3/F3,0) | R3: =IFERROR(H3/G3,0)
A4: School Management System | B4: =SUMIFS(Cleaned_Daily!$F$2:$F$3047,Cleaned_Daily!$E$2:$E$3047,$A4) | C4: =SUMIFS(Cleaned_Daily!$G$2:$G$3047,Cleaned_Daily!$E$2:$E$3047,$A4) | D4: =SUMIFS(Cleaned_Daily!$H$2:$H$3047,Cleaned_Daily!$E$2:$E$3047,$A4) | E4: =SUMIFS(Cleaned_Daily!$I$2:$I$3047,Cleaned_Daily!$E$2:$E$3047,$A4) | F4: =SUMIFS(Cleaned_Daily!$J$2:$J$3047,Cleaned_Daily!$E$2:$E$3047,$A4) | G4: =SUMIFS(Cleaned_Daily!$K$2:$K$3047,Cleaned_Daily!$E$2:$E$3047,$A4) | H4: =SUMIFS(Cleaned_Daily!$L$2:$L$3047,Cleaned_Daily!$E$2:$E$3047,$A4) | I4: =SUMIFS(Cleaned_Daily!$M$2:$M$3047,Cleaned_Daily!$E$2:$E$3047,$A4) | J4: =IFERROR(D4/C4,0) | K4: =IFERROR(B4/D4,0) | L4: =IFERROR(F4/D4,0) | M4: =IFERROR(B4/F4,0) | N4: =IFERROR(B4/G4,0) | O4: =IFERROR(I4/B4,0) | P4: =IFERROR((I4-B4)/B4,0) | Q4: =IFERROR(G4/F4,0) | R4: =IFERROR(H4/G4,0)
A5: Business Automation | B5: =SUMIFS(Cleaned_Daily!$F$2:$F$3047,Cleaned_Daily!$E$2:$E$3047,$A5) | C5: =SUMIFS(Cleaned_Daily!$G$2:$G$3047,Cleaned_Daily!$E$2:$E$3047,$A5) | D5: =SUMIFS(Cleaned_Daily!$H$2:$H$3047,Cleaned_Daily!$E$2:$E$3047,$A5) | E5: =SUMIFS(Cleaned_Daily!$I$2:$I$3047,Cleaned_Daily!$E$2:$E$3047,$A5) | F5: =SUMIFS(Cleaned_Daily!$J$2:$J$3047,Cleaned_Daily!$E$2:$E$3047,$A5) | G5: =SUMIFS(Cleaned_Daily!$K$2:$K$3047,Cleaned_Daily!$E$2:$E$3047,$A5) | H5: =SUMIFS(Cleaned_Daily!$L$2:$L$3047,Cleaned_Daily!$E$2:$E$3047,$A5) | I5: =SUMIFS(Cleaned_Daily!$M$2:$M$3047,Cleaned_Daily!$E$2:$E$3047,$A5) | J5: =IFERROR(D5/C5,0) | K5: =IFERROR(B5/D5,0) | L5: =IFERROR(F5/D5,0) | M5: =IFERROR(B5/F5,0) | N5: =IFERROR(B5/G5,0) | O5: =IFERROR(I5/B5,0) | P5: =IFERROR((I5-B5)/B5,0) | Q5: =IFERROR(G5/F5,0) | R5: =IFERROR(H5/G5,0)
A6: SEO Services | B6: =SUMIFS(Cleaned_Daily!$F$2:$F$3047,Cleaned_Daily!$E$2:$E$3047,$A6) | C6: =SUMIFS(Cleaned_Daily!$G$2:$G$3047,Cleaned_Daily!$E$2:$E$3047,$A6) | D6: =SUMIFS(Cleaned_Daily!$H$2:$H$3047,Cleaned_Daily!$E$2:$E$3047,$A6) | E6: =SUMIFS(Cleaned_Daily!$I$2:$I$3047,Cleaned_Daily!$E$2:$E$3047,$A6) | F6: =SUMIFS(Cleaned_Daily!$J$2:$J$3047,Cleaned_Daily!$E$2:$E$3047,$A6) | G6: =SUMIFS(Cleaned_Daily!$K$2:$K$3047,Cleaned_Daily!$E$2:$E$3047,$A6) | H6: =SUMIFS(Cleaned_Daily!$L$2:$L$3047,Cleaned_Daily!$E$2:$E$3047,$A6) | I6: =SUMIFS(Cleaned_Daily!$M$2:$M$3047,Cleaned_Daily!$E$2:$E$3047,$A6) | J6: =IFERROR(D6/C6,0) | K6: =IFERROR(B6/D6,0) | L6: =IFERROR(F6/D6,0) | M6: =IFERROR(B6/F6,0) | N6: =IFERROR(B6/G6,0) | O6: =IFERROR(I6/B6,0) | P6: =IFERROR((I6-B6)/B6,0) | Q6: =IFERROR(G6/F6,0) | R6: =IFERROR(H6/G6,0)
A7: News Portal Development | B7: =SUMIFS(Cleaned_Daily!$F$2:$F$3047,Cleaned_Daily!$E$2:$E$3047,$A7) | C7: =SUMIFS(Cleaned_Daily!$G$2:$G$3047,Cleaned_Daily!$E$2:$E$3047,$A7) | D7: =SUMIFS(Cleaned_Daily!$H$2:$H$3047,Cleaned_Daily!$E$2:$E$3047,$A7) | E7: =SUMIFS(Cleaned_Daily!$I$2:$I$3047,Cleaned_Daily!$E$2:$E$3047,$A7) | F7: =SUMIFS(Cleaned_Daily!$J$2:$J$3047,Cleaned_Daily!$E$2:$E$3047,$A7) | G7: =SUMIFS(Cleaned_Daily!$K$2:$K$3047,Cleaned_Daily!$E$2:$E$3047,$A7) | H7: =SUMIFS(Cleaned_Daily!$L$2:$L$3047,Cleaned_Daily!$E$2:$E$3047,$A7) | I7: =SUMIFS(Cleaned_Daily!$M$2:$M$3047,Cleaned_Daily!$E$2:$E$3047,$A7) | J7: =IFERROR(D7/C7,0) | K7: =IFERROR(B7/D7,0) | L7: =IFERROR(F7/D7,0) | M7: =IFERROR(B7/F7,0) | N7: =IFERROR(B7/G7,0) | O7: =IFERROR(I7/B7,0) | P7: =IFERROR((I7-B7)/B7,0) | Q7: =IFERROR(G7/F7,0) | R7: =IFERROR(H7/G7,0)
A8: Social Media Marketing | B8: =SUMIFS(Cleaned_Daily!$F$2:$F$3047,Cleaned_Daily!$E$2:$E$3047,$A8) | C8: =SUMIFS(Cleaned_Daily!$G$2:$G$3047,Cleaned_Daily!$E$2:$E$3047,$A8) | D8: =SUMIFS(Cleaned_Daily!$H$2:$H$3047,Cleaned_Daily!$E$2:$E$3047,$A8) | E8: =SUMIFS(Cleaned_Daily!$I$2:$I$3047,Cleaned_Daily!$E$2:$E$3047,$A8) | F8: =SUMIFS(Cleaned_Daily!$J$2:$J$3047,Cleaned_Daily!$E$2:$E$3047,$A8) | G8: =SUMIFS(Cleaned_Daily!$K$2:$K$3047,Cleaned_Daily!$E$2:$E$3047,$A8) | H8: =SUMIFS(Cleaned_Daily!$L$2:$L$3047,Cleaned_Daily!$E$2:$E$3047,$A8) | I8: =SUMIFS(Cleaned_Daily!$M$2:$M$3047,Cleaned_Daily!$E$2:$E$3047,$A8) | J8: =IFERROR(D8/C8,0) | K8: =IFERROR(B8/D8,0) | L8: =IFERROR(F8/D8,0) | M8: =IFERROR(B8/F8,0) | N8: =IFERROR(B8/G8,0) | O8: =IFERROR(I8/B8,0) | P8: =IFERROR((I8-B8)/B8,0) | Q8: =IFERROR(G8/F8,0) | R8: =IFERROR(H8/G8,0)
A9: Branding & Design | B9: =SUMIFS(Cleaned_Daily!$F$2:$F$3047,Cleaned_Daily!$E$2:$E$3047,$A9) | C9: =SUMIFS(Cleaned_Daily!$G$2:$G$3047,Cleaned_Daily!$E$2:$E$3047,$A9) | D9: =SUMIFS(Cleaned_Daily!$H$2:$H$3047,Cleaned_Daily!$E$2:$E$3047,$A9) | E9: =SUMIFS(Cleaned_Daily!$I$2:$I$3047,Cleaned_Daily!$E$2:$E$3047,$A9) | F9: =SUMIFS(Cleaned_Daily!$J$2:$J$3047,Cleaned_Daily!$E$2:$E$3047,$A9) | G9: =SUMIFS(Cleaned_Daily!$K$2:$K$3047,Cleaned_Daily!$E$2:$E$3047,$A9) | H9: =SUMIFS(Cleaned_Daily!$L$2:$L$3047,Cleaned_Daily!$E$2:$E$3047,$A9) | I9: =SUMIFS(Cleaned_Daily!$M$2:$M$3047,Cleaned_Daily!$E$2:$E$3047,$A9) | J9: =IFERROR(D9/C9,0) | K9: =IFERROR(B9/D9,0) | L9: =IFERROR(F9/D9,0) | M9: =IFERROR(B9/F9,0) | N9: =IFERROR(B9/G9,0) | O9: =IFERROR(I9/B9,0) | P9: =IFERROR((I9-B9)/B9,0) | Q9: =IFERROR(G9/F9,0) | R9: =IFERROR(H9/G9,0)

Sheet Lead_Quality
A1: Channel | B1: Total Leads | C1: Qualified Leads | D1: Customers | E1: Qualification Rate | F1: Customer Rate from Qualified | G1: Average Lead Quality Score
A2: Direct | B2: 40 | C2: 14 | D2: 4 | E2: 0.35 | F2: 0.2857 | G2: 53
A3: Email | B3: 190 | C3: 65 | D3: 5 | E3: 0.3421 | F3: 0.0769 | G3: 51.8
A4: Facebook Ads | B4: 1142 | C4: 308 | D4: 32 | E4: 0.2697 | F4: 0.1039 | G4: 48.7
A5: Google Ads | B5: 2980 | C5: 1363 | D5: 221 | E5: 0.4574 | F5: 0.1621 | G5: 56.5
A6: Instagram Ads | B6: 397 | C6: 72 | D6: 7 | E6: 0.1814 | F6: 0.0972 | G6: 45.6
A7: SEO | B7: 659 | C7: 268 | D7: 39 | E7: 0.4067 | F7: 0.1455 | G7: 54.3

Sheet Recommendations
A1: Priority | B1: Finding | C1: Evidence | D1: Recommendation | E1: Expected business impact
A2: High | B2: Scale the strongest paid campaign | C2: Search_Sep24_School_System_Demo generated $63,459 revenue with ROAS 25.41. | D2: Move 15-20% of budget from weak paid campaigns into similar Google Search campaigns and keep monitoring lead quality. | E2: Higher revenue from the same monthly budget.
A3: High | B3: Reduce spend where qualified leads are too expensive | C3: DA_Jan24_eCommerce_Growth_Push has cost per qualified lead of $136.51. | D3: Pause weak ad sets/keywords, tighten audience targeting, and test a clearer offer before increasing spend. | E3: Lower wasted ad spend and better lead quality.
A4: Medium | B4: Fix campaigns with clicks but low conversion | C4: DA_Aug24_News_Portal_Leads produced 4,263 clicks but conversion rate was only 2.42%. | D4: Improve landing page headline, form length, trust signals, and service-specific call-to-action. | E4: More leads without increasing traffic cost.
A5: Medium | B5: Use lead quality, not lead volume alone | C5: Google Ads had a lead qualification rate of 45.74%. | D5: Create a lead quality dashboard and review qualified leads weekly with sales. | E5: Marketing and sales can agree on which channels deserve budget.
A6: Low | B6: Protect organic performance | C6: SEO generated qualified leads and revenue without direct media spend. | D6: Continue publishing service pages, case-study blogs, and FAQ content around high-demand services. | E6: More low-cost inbound leads over time.

Sheet Dashboard
A1: Marketing Campaign ROI Dashboard
A2: Realistic synthetic portfolio data | Dec 2023 - Dec 2024 | Digital solutions company
A3: Total Spend | B3: =SUM(Channel_KPIs!B2:B20) | D3: Channel | E3: Spend | F3: Leads | G3: Qual. Leads | H3: Revenue
A4: Total Revenue | B4: =SUM(Channel_KPIs!I2:I20) | D4: Google Ads | E4: =IFERROR(VLOOKUP($D4,Channel_KPIs!$A$2:$I$8,2,FALSE),"") | F4: =IFERROR(VLOOKUP($D4,Channel_KPIs!$A$2:$I$8,6,FALSE),"") | G4: =IFERROR(VLOOKUP($D4,Channel_KPIs!$A$2:$I$8,7,FALSE),"") | H4: =IFERROR(VLOOKUP($D4,Channel_KPIs!$A$2:$I$8,9,FALSE),"")
A5: Total Leads | B5: =SUM(Channel_KPIs!F2:F20) | D5: SEO | E5: =IFERROR(VLOOKUP($D5,Channel_KPIs!$A$2:$I$8,2,FALSE),"") | F5: =IFERROR(VLOOKUP($D5,Channel_KPIs!$A$2:$I$8,6,FALSE),"") | G5: =IFERROR(VLOOKUP($D5,Channel_KPIs!$A$2:$I$8,7,FALSE),"") | H5: =IFERROR(VLOOKUP($D5,Channel_KPIs!$A$2:$I$8,9,FALSE),"")
A6: Qualified Leads | B6: =SUM(Channel_KPIs!G2:G20) | D6: Facebook Ads | E6: =IFERROR(VLOOKUP($D6,Channel_KPIs!$A$2:$I$8,2,FALSE),"") | F6: =IFERROR(VLOOKUP($D6,Channel_KPIs!$A$2:$I$8,6,FALSE),"") | G6: =IFERROR(VLOOKUP($D6,Channel_KPIs!$A$2:$I$8,7,FALSE),"") | H6: =IFERROR(VLOOKUP($D6,Channel_KPIs!$A$2:$I$8,9,FALSE),"")
A7: Customers | B7: =SUM(Channel_KPIs!H2:H20) | D7: Direct | E7: =IFERROR(VLOOKUP($D7,Channel_KPIs!$A$2:$I$8,2,FALSE),"") | F7: =IFERROR(VLOOKUP($D7,Channel_KPIs!$A$2:$I$8,6,FALSE),"") | G7: =IFERROR(VLOOKUP($D7,Channel_KPIs!$A$2:$I$8,7,FALSE),"") | H7: =IFERROR(VLOOKUP($D7,Channel_KPIs!$A$2:$I$8,9,FALSE),"")
A8: Overall ROAS | B8: =IFERROR(B4/B3,0) | D8: Instagram Ads | E8: =IFERROR(VLOOKUP($D8,Channel_KPIs!$A$2:$I$8,2,FALSE),"") | F8: =IFERROR(VLOOKUP($D8,Channel_KPIs!$A$2:$I$8,6,FALSE),"") | G8: =IFERROR(VLOOKUP($D8,Channel_KPIs!$A$2:$I$8,7,FALSE),"") | H8: =IFERROR(VLOOKUP($D8,Channel_KPIs!$A$2:$I$8,9,FALSE),"")
A9: Overall ROI | B9: =IFERROR((B4-B3)/B3,0) | D9: Email | E9: =IFERROR(VLOOKUP($D9,Channel_KPIs!$A$2:$I$8,2,FALSE),"") | F9: =IFERROR(VLOOKUP($D9,Channel_KPIs!$A$2:$I$8,6,FALSE),"") | G9: =IFERROR(VLOOKUP($D9,Channel_KPIs!$A$2:$I$8,7,FALSE),"") | H9: =IFERROR(VLOOKUP($D9,Channel_KPIs!$A$2:$I$8,9,FALSE),"")
A10: Lead Quality Rate | B10: =IFERROR(B6/B5,0) | D10: Referral | E10: =IFERROR(VLOOKUP($D10,Channel_KPIs!$A$2:$I$8,2,FALSE),"") | F10: =IFERROR(VLOOKUP($D10,Channel_KPIs!$A$2:$I$8,6,FALSE),"") | G10: =IFERROR(VLOOKUP($D10,Channel_KPIs!$A$2:$I$8,7,FALSE),"") | H10: =IFERROR(VLOOKUP($D10,Channel_KPIs!$A$2:$I$8,9,FALSE),"")
A13: Main Business Findings
A14: 1 | B14: Google Ads generated the highest revenue and strongest paid ROAS, but still needs lead-quality monitoring.
A15: 2 | B15: Instagram Ads had weaker ROI because it produced cheaper attention but fewer qualified leads and customers.
A16: 3 | B16: SEO created lower-cost long-term value because it generated qualified leads without direct media spend.
A17: 4 | B17: Email had small spend and good efficiency, so it is useful for nurturing existing prospects.
A18: 5 | B18: The best recommendation is to reallocate budget based on cost per qualified lead, not only cost per lead.

Sheet QA_Checks
A1: Check | B1: Result | C1: Why it matters
A2: Meta Ads raw rows | B2: 1380 | C2: Confirms the Meta export loaded correctly.
A3: Google Ads raw rows | B3: 1035 | C3: Confirms the Google Ads export loaded correctly.
A4: Website traffic raw rows | B4: 3573 | C4: Confirms the GA4-style export loaded correctly.
A5: Email marketing raw rows | B5: 26 | C5: Confirms the email export loaded correctly.
A6: CRM lead rows | B6: 5408 | C6: Confirms the CRM lead export loaded correctly.
A7: Cleaned daily performance rows | B7: 3046 | C7: Confirms the final analysis table was created.
A8: Unique CRM lead IDs | B8: 5408 | C8: Should match total CRM rows if there are no duplicate lead IDs.
A9: Duplicate CRM lead IDs | B9: 0 | C9: Duplicate leads can overstate lead volume.
A10: Analysis date range | B10: 2023-12-01 to 2024-12-31 | C10: Confirms the project covers the intended period.
A11: Main join keys used | B11: Date + Channel + Platform + Campaign + Service | C11: Explains how raw platforms were connected to CRM outcomes.
